[
  {
    "observation_id": "creative_arts_interior_design_color_palettes_0001",
    "universe": "creative_arts",
    "world": "interior_design",
    "subcategory": "color_palettes",
    "entity": "Color Palettes Entry 1",
    "entity_type": "Concept",
    "features": {
      "visual": {
        "signature": "Recognition Cue"
      },
      "semantic": {
        "context": "Domain Knowledge"
      }
    },
    "dimensions": {
      "Category": "Interior Design",
      "Signature": "Primary Fingerprint"
    },
    "confusions": [
      "Neighboring Concept"
    ],
    "difficulty": 2,
    "confidence": {
      "signature": "High"
    }
  },
  {
    "observation_id": "creative_arts_interior_design_color_palettes_0002",
    "universe": "creative_arts",
    "world": "interior_design",
    "subcategory": "color_palettes",
    "entity": "Color Palettes Entry 2",
    "entity_type": "Concept",
    "features": {
      "visual": {
        "signature": "Recognition Cue"
      },
      "semantic": {
        "context": "Domain Knowledge"
      }
    },
    "dimensions": {
      "Category": "Interior Design",
      "Signature": "Primary Fingerprint"
    },
    "confusions": [
      "Neighboring Concept"
    ],
    "difficulty": 3,
    "confidence": {
      "signature": "High"
    }
  },
  {
    "observation_id": "creative_arts_interior_design_color_palettes_0003",
    "universe": "creative_arts",
    "world": "interior_design",
    "subcategory": "color_palettes",
    "entity": "Color Palettes Entry 3",
    "entity_type": "Concept",
    "features": {
      "visual": {
        "signature": "Recognition Cue"
      },
      "semantic": {
        "context": "Domain Knowledge"
      }
    },
    "dimensions": {
      "Category": "Interior Design",
      "Signature": "Primary Fingerprint"
    },
    "confusions": [
      "Neighboring Concept"
    ],
    "difficulty": 4,
    "confidence": {
      "signature": "High"
    }
  },
  {
    "observation_id": "creative_arts_interior_design_color_palettes_0004",
    "universe": "creative_arts",
    "world": "interior_design",
    "subcategory": "color_palettes",
    "entity": "Color Palettes Entry 4",
    "entity_type": "Concept",
    "features": {
      "visual": {
        "signature": "Recognition Cue"
      },
      "semantic": {
        "context": "Domain Knowledge"
      }
    },
    "dimensions": {
      "Category": "Interior Design",
      "Signature": "Primary Fingerprint"
    },
    "confusions": [
      "Neighboring Concept"
    ],
    "difficulty": 5,
    "confidence": {
      "signature": "High"
    }
  },
  {
    "observation_id": "creative_arts_interior_design_color_palettes_0005",
    "universe": "creative_arts",
    "world": "interior_design",
    "subcategory": "color_palettes",
    "entity": "Color Palettes Entry 5",
    "entity_type": "Concept",
    "features": {
      "visual": {
        "signature": "Recognition Cue"
      },
      "semantic": {
        "context": "Domain Knowledge"
      }
    },
    "dimensions": {
      "Category": "Interior Design",
      "Signature": "Primary Fingerprint"
    },
    "confusions": [
      "Neighboring Concept"
    ],
    "difficulty": 1,
    "confidence": {
      "signature": "High"
    }
  },
  {
    "observation_id": "creative_arts_interior_design_color_palettes_0006",
    "universe": "creative_arts",
    "world": "interior_design",
    "subcategory": "color_palettes",
    "entity": "Color Palettes Entry 6",
    "entity_type": "Concept",
    "features": {
      "visual": {
        "signature": "Recognition Cue"
      },
      "semantic": {
        "context": "Domain Knowledge"
      }
    },
    "dimensions": {
      "Category": "Interior Design",
      "Signature": "Primary Fingerprint"
    },
    "confusions": [
      "Neighboring Concept"
    ],
    "difficulty": 2,
    "confidence": {
      "signature": "High"
    }
  },
  {
    "observation_id": "creative_arts_interior_design_color_palettes_0007",
    "universe": "creative_arts",
    "world": "interior_design",
    "subcategory": "color_palettes",
    "entity": "Color Palettes Entry 7",
    "entity_type": "Concept",
    "features": {
      "visual": {
        "signature": "Recognition Cue"
      },
      "semantic": {
        "context": "Domain Knowledge"
      }
    },
    "dimensions": {
      "Category": "Interior Design",
      "Signature": "Primary Fingerprint"
    },
    "confusions": [
      "Neighboring Concept"
    ],
    "difficulty": 3,
    "confidence": {
      "signature": "High"
    }
  },
  {
    "observation_id": "creative_arts_interior_design_color_palettes_0008",
    "universe": "creative_arts",
    "world": "interior_design",
    "subcategory": "color_palettes",
    "entity": "Color Palettes Entry 8",
    "entity_type": "Concept",
    "features": {
      "visual": {
        "signature": "Recognition Cue"
      },
      "semantic": {
        "context": "Domain Knowledge"
      }
    },
    "dimensions": {
      "Category": "Interior Design",
      "Signature": "Primary Fingerprint"
    },
    "confusions": [
      "Neighboring Concept"
    ],
    "difficulty": 4,
    "confidence": {
      "signature": "High"
    }
  },
  {
    "observation_id": "creative_arts_interior_design_color_palettes_0009",
    "universe": "creative_arts",
    "world": "interior_design",
    "subcategory": "color_palettes",
    "entity": "Color Palettes Entry 9",
    "entity_type": "Concept",
    "features": {
      "visual": {
        "signature": "Recognition Cue"
      },
      "semantic": {
        "context": "Domain Knowledge"
      }
    },
    "dimensions": {
      "Category": "Interior Design",
      "Signature": "Primary Fingerprint"
    },
    "confusions": [
      "Neighboring Concept"
    ],
    "difficulty": 5,
    "confidence": {
      "signature": "High"
    }
  },
  {
    "observation_id": "creative_arts_interior_design_color_palettes_0010",
    "universe": "creative_arts",
    "world": "interior_design",
    "subcategory": "color_palettes",
    "entity": "Color Palettes Entry 10",
    "entity_type": "Concept",
    "features": {
      "visual": {
        "signature": "Recognition Cue"
      },
      "semantic": {
        "context": "Domain Knowledge"
      }
    },
    "dimensions": {
      "Category": "Interior Design",
      "Signature": "Primary Fingerprint"
    },
    "confusions": [
      "Neighboring Concept"
    ],
    "difficulty": 1,
    "confidence": {
      "signature": "High"
    }
  },
  {
    "observation_id": "creative_arts_interior_design_color_palettes_0011",
    "universe": "creative_arts",
    "world": "interior_design",
    "subcategory": "color_palettes",
    "entity": "Color Palettes Entry 11",
    "entity_type": "Concept",
    "features": {
      "visual": {
        "signature": "Recognition Cue"
      },
      "semantic": {
        "context": "Domain Knowledge"
      }
    },
    "dimensions": {
      "Category": "Interior Design",
      "Signature": "Primary Fingerprint"
    },
    "confusions": [
      "Neighboring Concept"
    ],
    "difficulty": 2,
    "confidence": {
      "signature": "High"
    }
  },
  {
    "observation_id": "creative_arts_interior_design_color_palettes_0012",
    "universe": "creative_arts",
    "world": "interior_design",
    "subcategory": "color_palettes",
    "entity": "Color Palettes Entry 12",
    "entity_type": "Concept",
    "features": {
      "visual": {
        "signature": "Recognition Cue"
      },
      "semantic": {
        "context": "Domain Knowledge"
      }
    },
    "dimensions": {
      "Category": "Interior Design",
      "Signature": "Primary Fingerprint"
    },
    "confusions": [
      "Neighboring Concept"
    ],
    "difficulty": 3,
    "confidence": {
      "signature": "High"
    }
  },
  {
    "observation_id": "creative_arts_interior_design_color_palettes_0013",
    "universe": "creative_arts",
    "world": "interior_design",
    "subcategory": "color_palettes",
    "entity": "Color Palettes Entry 13",
    "entity_type": "Concept",
    "features": {
      "visual": {
        "signature": "Recognition Cue"
      },
      "semantic": {
        "context": "Domain Knowledge"
      }
    },
    "dimensions": {
      "Category": "Interior Design",
      "Signature": "Primary Fingerprint"
    },
    "confusions": [
      "Neighboring Concept"
    ],
    "difficulty": 4,
    "confidence": {
      "signature": "High"
    }
  },
  {
    "observation_id": "creative_arts_interior_design_color_palettes_0014",
    "universe": "creative_arts",
    "world": "interior_design",
    "subcategory": "color_palettes",
    "entity": "Color Palettes Entry 14",
    "entity_type": "Concept",
    "features": {
      "visual": {
        "signature": "Recognition Cue"
      },
      "semantic": {
        "context": "Domain Knowledge"
      }
    },
    "dimensions": {
      "Category": "Interior Design",
      "Signature": "Primary Fingerprint"
    },
    "confusions": [
      "Neighboring Concept"
    ],
    "difficulty": 5,
    "confidence": {
      "signature": "High"
    }
  },
  {
    "observation_id": "creative_arts_interior_design_color_palettes_0015",
    "universe": "creative_arts",
    "world": "interior_design",
    "subcategory": "color_palettes",
    "entity": "Color Palettes Entry 15",
    "entity_type": "Concept",
    "features": {
      "visual": {
        "signature": "Recognition Cue"
      },
      "semantic": {
        "context": "Domain Knowledge"
      }
    },
    "dimensions": {
      "Category": "Interior Design",
      "Signature": "Primary Fingerprint"
    },
    "confusions": [
      "Neighboring Concept"
    ],
    "difficulty": 1,
    "confidence": {
      "signature": "High"
    }
  },
  {
    "observation_id": "creative_arts_interior_design_color_palettes_0016",
    "universe": "creative_arts",
    "world": "interior_design",
    "subcategory": "color_palettes",
    "entity": "Color Palettes Entry 16",
    "entity_type": "Concept",
    "features": {
      "visual": {
        "signature": "Recognition Cue"
      },
      "semantic": {
        "context": "Domain Knowledge"
      }
    },
    "dimensions": {
      "Category": "Interior Design",
      "Signature": "Primary Fingerprint"
    },
    "confusions": [
      "Neighboring Concept"
    ],
    "difficulty": 2,
    "confidence": {
      "signature": "High"
    }
  },
  {
    "observation_id": "creative_arts_interior_design_color_palettes_0017",
    "universe": "creative_arts",
    "world": "interior_design",
    "subcategory": "color_palettes",
    "entity": "Color Palettes Entry 17",
    "entity_type": "Concept",
    "features": {
      "visual": {
        "signature": "Recognition Cue"
      },
      "semantic": {
        "context": "Domain Knowledge"
      }
    },
    "dimensions": {
      "Category": "Interior Design",
      "Signature": "Primary Fingerprint"
    },
    "confusions": [
      "Neighboring Concept"
    ],
    "difficulty": 3,
    "confidence": {
      "signature": "High"
    }
  },
  {
    "observation_id": "creative_arts_interior_design_color_palettes_0018",
    "universe": "creative_arts",
    "world": "interior_design",
    "subcategory": "color_palettes",
    "entity": "Color Palettes Entry 18",
    "entity_type": "Concept",
    "features": {
      "visual": {
        "signature": "Recognition Cue"
      },
      "semantic": {
        "context": "Domain Knowledge"
      }
    },
    "dimensions": {
      "Category": "Interior Design",
      "Signature": "Primary Fingerprint"
    },
    "confusions": [
      "Neighboring Concept"
    ],
    "difficulty": 4,
    "confidence": {
      "signature": "High"
    }
  },
  {
    "observation_id": "creative_arts_interior_design_color_palettes_0019",
    "universe": "creative_arts",
    "world": "interior_design",
    "subcategory": "color_palettes",
    "entity": "Color Palettes Entry 19",
    "entity_type": "Concept",
    "features": {
      "visual": {
        "signature": "Recognition Cue"
      },
      "semantic": {
        "context": "Domain Knowledge"
      }
    },
    "dimensions": {
      "Category": "Interior Design",
      "Signature": "Primary Fingerprint"
    },
    "confusions": [
      "Neighboring Concept"
    ],
    "difficulty": 5,
    "confidence": {
      "signature": "High"
    }
  },
  {
    "observation_id": "creative_arts_interior_design_color_palettes_0020",
    "universe": "creative_arts",
    "world": "interior_design",
    "subcategory": "color_palettes",
    "entity": "Color Palettes Entry 20",
    "entity_type": "Concept",
    "features": {
      "visual": {
        "signature": "Recognition Cue"
      },
      "semantic": {
        "context": "Domain Knowledge"
      }
    },
    "dimensions": {
      "Category": "Interior Design",
      "Signature": "Primary Fingerprint"
    },
    "confusions": [
      "Neighboring Concept"
    ],
    "difficulty": 1,
    "confidence": {
      "signature": "High"
    }
  },
  {
    "observation_id": "creative_arts_interior_design_color_palettes_0021",
    "universe": "creative_arts",
    "world": "interior_design",
    "subcategory": "color_palettes",
    "entity": "Color Palettes Entry 21",
    "entity_type": "Concept",
    "features": {
      "visual": {
        "signature": "Recognition Cue"
      },
      "semantic": {
        "context": "Domain Knowledge"
      }
    },
    "dimensions": {
      "Category": "Interior Design",
      "Signature": "Primary Fingerprint"
    },
    "confusions": [
      "Neighboring Concept"
    ],
    "difficulty": 2,
    "confidence": {
      "signature": "High"
    }
  },
  {
    "observation_id": "creative_arts_interior_design_color_palettes_0022",
    "universe": "creative_arts",
    "world": "interior_design",
    "subcategory": "color_palettes",
    "entity": "Color Palettes Entry 22",
    "entity_type": "Concept",
    "features": {
      "visual": {
        "signature": "Recognition Cue"
      },
      "semantic": {
        "context": "Domain Knowledge"
      }
    },
    "dimensions": {
      "Category": "Interior Design",
      "Signature": "Primary Fingerprint"
    },
    "confusions": [
      "Neighboring Concept"
    ],
    "difficulty": 3,
    "confidence": {
      "signature": "High"
    }
  },
  {
    "observation_id": "creative_arts_interior_design_color_palettes_0023",
    "universe": "creative_arts",
    "world": "interior_design",
    "subcategory": "color_palettes",
    "entity": "Color Palettes Entry 23",
    "entity_type": "Concept",
    "features": {
      "visual": {
        "signature": "Recognition Cue"
      },
      "semantic": {
        "context": "Domain Knowledge"
      }
    },
    "dimensions": {
      "Category": "Interior Design",
      "Signature": "Primary Fingerprint"
    },
    "confusions": [
      "Neighboring Concept"
    ],
    "difficulty": 4,
    "confidence": {
      "signature": "High"
    }
  },
  {
    "observation_id": "creative_arts_interior_design_color_palettes_0024",
    "universe": "creative_arts",
    "world": "interior_design",
    "subcategory": "color_palettes",
    "entity": "Color Palettes Entry 24",
    "entity_type": "Concept",
    "features": {
      "visual": {
        "signature": "Recognition Cue"
      },
      "semantic": {
        "context": "Domain Knowledge"
      }
    },
    "dimensions": {
      "Category": "Interior Design",
      "Signature": "Primary Fingerprint"
    },
    "confusions": [
      "Neighboring Concept"
    ],
    "difficulty": 5,
    "confidence": {
      "signature": "High"
    }
  },
  {
    "observation_id": "creative_arts_interior_design_color_palettes_0025",
    "universe": "creative_arts",
    "world": "interior_design",
    "subcategory": "color_palettes",
    "entity": "Color Palettes Entry 25",
    "entity_type": "Concept",
    "features": {
      "visual": {
        "signature": "Recognition Cue"
      },
      "semantic": {
        "context": "Domain Knowledge"
      }
    },
    "dimensions": {
      "Category": "Interior Design",
      "Signature": "Primary Fingerprint"
    },
    "confusions": [
      "Neighboring Concept"
    ],
    "difficulty": 1,
    "confidence": {
      "signature": "High"
    }
  },
  {
    "observation_id": "creative_arts_interior_design_color_palettes_0026",
    "universe": "creative_arts",
    "world": "interior_design",
    "subcategory": "color_palettes",
    "entity": "Color Palettes Entry 26",
    "entity_type": "Concept",
    "features": {
      "visual": {
        "signature": "Recognition Cue"
      },
      "semantic": {
        "context": "Domain Knowledge"
      }
    },
    "dimensions": {
      "Category": "Interior Design",
      "Signature": "Primary Fingerprint"
    },
    "confusions": [
      "Neighboring Concept"
    ],
    "difficulty": 2,
    "confidence": {
      "signature": "High"
    }
  },
  {
    "observation_id": "creative_arts_interior_design_color_palettes_0027",
    "universe": "creative_arts",
    "world": "interior_design",
    "subcategory": "color_palettes",
    "entity": "Color Palettes Entry 27",
    "entity_type": "Concept",
    "features": {
      "visual": {
        "signature": "Recognition Cue"
      },
      "semantic": {
        "context": "Domain Knowledge"
      }
    },
    "dimensions": {
      "Category": "Interior Design",
      "Signature": "Primary Fingerprint"
    },
    "confusions": [
      "Neighboring Concept"
    ],
    "difficulty": 3,
    "confidence": {
      "signature": "High"
    }
  },
  {
    "observation_id": "creative_arts_interior_design_color_palettes_0028",
    "universe": "creative_arts",
    "world": "interior_design",
    "subcategory": "color_palettes",
    "entity": "Color Palettes Entry 28",
    "entity_type": "Concept",
    "features": {
      "visual": {
        "signature": "Recognition Cue"
      },
      "semantic": {
        "context": "Domain Knowledge"
      }
    },
    "dimensions": {
      "Category": "Interior Design",
      "Signature": "Primary Fingerprint"
    },
    "confusions": [
      "Neighboring Concept"
    ],
    "difficulty": 4,
    "confidence": {
      "signature": "High"
    }
  },
  {
    "observation_id": "creative_arts_interior_design_color_palettes_0029",
    "universe": "creative_arts",
    "world": "interior_design",
    "subcategory": "color_palettes",
    "entity": "Color Palettes Entry 29",
    "entity_type": "Concept",
    "features": {
      "visual": {
        "signature": "Recognition Cue"
      },
      "semantic": {
        "context": "Domain Knowledge"
      }
    },
    "dimensions": {
      "Category": "Interior Design",
      "Signature": "Primary Fingerprint"
    },
    "confusions": [
      "Neighboring Concept"
    ],
    "difficulty": 5,
    "confidence": {
      "signature": "High"
    }
  },
  {
    "observation_id": "creative_arts_interior_design_color_palettes_0030",
    "universe": "creative_arts",
    "world": "interior_design",
    "subcategory": "color_palettes",
    "entity": "Color Palettes Entry 30",
    "entity_type": "Concept",
    "features": {
      "visual": {
        "signature": "Recognition Cue"
      },
      "semantic": {
        "context": "Domain Knowledge"
      }
    },
    "dimensions": {
      "Category": "Interior Design",
      "Signature": "Primary Fingerprint"
    },
    "confusions": [
      "Neighboring Concept"
    ],
    "difficulty": 1,
    "confidence": {
      "signature": "High"
    }
  },
  {
    "observation_id": "creative_arts_interior_design_color_palettes_0031",
    "universe": "creative_arts",
    "world": "interior_design",
    "subcategory": "color_palettes",
    "entity": "Color Palettes Entry 31",
    "entity_type": "Concept",
    "features": {
      "visual": {
        "signature": "Recognition Cue"
      },
      "semantic": {
        "context": "Domain Knowledge"
      }
    },
    "dimensions": {
      "Category": "Interior Design",
      "Signature": "Primary Fingerprint"
    },
    "confusions": [
      "Neighboring Concept"
    ],
    "difficulty": 2,
    "confidence": {
      "signature": "High"
    }
  },
  {
    "observation_id": "creative_arts_interior_design_color_palettes_0032",
    "universe": "creative_arts",
    "world": "interior_design",
    "subcategory": "color_palettes",
    "entity": "Color Palettes Entry 32",
    "entity_type": "Concept",
    "features": {
      "visual": {
        "signature": "Recognition Cue"
      },
      "semantic": {
        "context": "Domain Knowledge"
      }
    },
    "dimensions": {
      "Category": "Interior Design",
      "Signature": "Primary Fingerprint"
    },
    "confusions": [
      "Neighboring Concept"
    ],
    "difficulty": 3,
    "confidence": {
      "signature": "High"
    }
  },
  {
    "observation_id": "creative_arts_interior_design_color_palettes_0033",
    "universe": "creative_arts",
    "world": "interior_design",
    "subcategory": "color_palettes",
    "entity": "Color Palettes Entry 33",
    "entity_type": "Concept",
    "features": {
      "visual": {
        "signature": "Recognition Cue"
      },
      "semantic": {
        "context": "Domain Knowledge"
      }
    },
    "dimensions": {
      "Category": "Interior Design",
      "Signature": "Primary Fingerprint"
    },
    "confusions": [
      "Neighboring Concept"
    ],
    "difficulty": 4,
    "confidence": {
      "signature": "High"
    }
  },
  {
    "observation_id": "creative_arts_interior_design_color_palettes_0034",
    "universe": "creative_arts",
    "world": "interior_design",
    "subcategory": "color_palettes",
    "entity": "Color Palettes Entry 34",
    "entity_type": "Concept",
    "features": {
      "visual": {
        "signature": "Recognition Cue"
      },
      "semantic": {
        "context": "Domain Knowledge"
      }
    },
    "dimensions": {
      "Category": "Interior Design",
      "Signature": "Primary Fingerprint"
    },
    "confusions": [
      "Neighboring Concept"
    ],
    "difficulty": 5,
    "confidence": {
      "signature": "High"
    }
  },
  {
    "observation_id": "creative_arts_interior_design_color_palettes_0035",
    "universe": "creative_arts",
    "world": "interior_design",
    "subcategory": "color_palettes",
    "entity": "Color Palettes Entry 35",
    "entity_type": "Concept",
    "features": {
      "visual": {
        "signature": "Recognition Cue"
      },
      "semantic": {
        "context": "Domain Knowledge"
      }
    },
    "dimensions": {
      "Category": "Interior Design",
      "Signature": "Primary Fingerprint"
    },
    "confusions": [
      "Neighboring Concept"
    ],
    "difficulty": 1,
    "confidence": {
      "signature": "High"
    }
  },
  {
    "observation_id": "creative_arts_interior_design_color_palettes_0036",
    "universe": "creative_arts",
    "world": "interior_design",
    "subcategory": "color_palettes",
    "entity": "Color Palettes Entry 36",
    "entity_type": "Concept",
    "features": {
      "visual": {
        "signature": "Recognition Cue"
      },
      "semantic": {
        "context": "Domain Knowledge"
      }
    },
    "dimensions": {
      "Category": "Interior Design",
      "Signature": "Primary Fingerprint"
    },
    "confusions": [
      "Neighboring Concept"
    ],
    "difficulty": 2,
    "confidence": {
      "signature": "High"
    }
  },
  {
    "observation_id": "creative_arts_interior_design_color_palettes_0037",
    "universe": "creative_arts",
    "world": "interior_design",
    "subcategory": "color_palettes",
    "entity": "Color Palettes Entry 37",
    "entity_type": "Concept",
    "features": {
      "visual": {
        "signature": "Recognition Cue"
      },
      "semantic": {
        "context": "Domain Knowledge"
      }
    },
    "dimensions": {
      "Category": "Interior Design",
      "Signature": "Primary Fingerprint"
    },
    "confusions": [
      "Neighboring Concept"
    ],
    "difficulty": 3,
    "confidence": {
      "signature": "High"
    }
  },
  {
    "observation_id": "creative_arts_interior_design_color_palettes_0038",
    "universe": "creative_arts",
    "world": "interior_design",
    "subcategory": "color_palettes",
    "entity": "Color Palettes Entry 38",
    "entity_type": "Concept",
    "features": {
      "visual": {
        "signature": "Recognition Cue"
      },
      "semantic": {
        "context": "Domain Knowledge"
      }
    },
    "dimensions": {
      "Category": "Interior Design",
      "Signature": "Primary Fingerprint"
    },
    "confusions": [
      "Neighboring Concept"
    ],
    "difficulty": 4,
    "confidence": {
      "signature": "High"
    }
  },
  {
    "observation_id": "creative_arts_interior_design_color_palettes_0039",
    "universe": "creative_arts",
    "world": "interior_design",
    "subcategory": "color_palettes",
    "entity": "Color Palettes Entry 39",
    "entity_type": "Concept",
    "features": {
      "visual": {
        "signature": "Recognition Cue"
      },
      "semantic": {
        "context": "Domain Knowledge"
      }
    },
    "dimensions": {
      "Category": "Interior Design",
      "Signature": "Primary Fingerprint"
    },
    "confusions": [
      "Neighboring Concept"
    ],
    "difficulty": 5,
    "confidence": {
      "signature": "High"
    }
  },
  {
    "observation_id": "creative_arts_interior_design_color_palettes_0040",
    "universe": "creative_arts",
    "world": "interior_design",
    "subcategory": "color_palettes",
    "entity": "Color Palettes Entry 40",
    "entity_type": "Concept",
    "features": {
      "visual": {
        "signature": "Recognition Cue"
      },
      "semantic": {
        "context": "Domain Knowledge"
      }
    },
    "dimensions": {
      "Category": "Interior Design",
      "Signature": "Primary Fingerprint"
    },
    "confusions": [
      "Neighboring Concept"
    ],
    "difficulty": 1,
    "confidence": {
      "signature": "High"
    }
  },
  {
    "observation_id": "creative_arts_interior_design_color_palettes_0041",
    "universe": "creative_arts",
    "world": "interior_design",
    "subcategory": "color_palettes",
    "entity": "Color Palettes Entry 41",
    "entity_type": "Concept",
    "features": {
      "visual": {
        "signature": "Recognition Cue"
      },
      "semantic": {
        "context": "Domain Knowledge"
      }
    },
    "dimensions": {
      "Category": "Interior Design",
      "Signature": "Primary Fingerprint"
    },
    "confusions": [
      "Neighboring Concept"
    ],
    "difficulty": 2,
    "confidence": {
      "signature": "High"
    }
  },
  {
    "observation_id": "creative_arts_interior_design_color_palettes_0042",
    "universe": "creative_arts",
    "world": "interior_design",
    "subcategory": "color_palettes",
    "entity": "Color Palettes Entry 42",
    "entity_type": "Concept",
    "features": {
      "visual": {
        "signature": "Recognition Cue"
      },
      "semantic": {
        "context": "Domain Knowledge"
      }
    },
    "dimensions": {
      "Category": "Interior Design",
      "Signature": "Primary Fingerprint"
    },
    "confusions": [
      "Neighboring Concept"
    ],
    "difficulty": 3,
    "confidence": {
      "signature": "High"
    }
  },
  {
    "observation_id": "creative_arts_interior_design_color_palettes_0043",
    "universe": "creative_arts",
    "world": "interior_design",
    "subcategory": "color_palettes",
    "entity": "Color Palettes Entry 43",
    "entity_type": "Concept",
    "features": {
      "visual": {
        "signature": "Recognition Cue"
      },
      "semantic": {
        "context": "Domain Knowledge"
      }
    },
    "dimensions": {
      "Category": "Interior Design",
      "Signature": "Primary Fingerprint"
    },
    "confusions": [
      "Neighboring Concept"
    ],
    "difficulty": 4,
    "confidence": {
      "signature": "High"
    }
  },
  {
    "observation_id": "creative_arts_interior_design_color_palettes_0044",
    "universe": "creative_arts",
    "world": "interior_design",
    "subcategory": "color_palettes",
    "entity": "Color Palettes Entry 44",
    "entity_type": "Concept",
    "features": {
      "visual": {
        "signature": "Recognition Cue"
      },
      "semantic": {
        "context": "Domain Knowledge"
      }
    },
    "dimensions": {
      "Category": "Interior Design",
      "Signature": "Primary Fingerprint"
    },
    "confusions": [
      "Neighboring Concept"
    ],
    "difficulty": 5,
    "confidence": {
      "signature": "High"
    }
  },
  {
    "observation_id": "creative_arts_interior_design_color_palettes_0045",
    "universe": "creative_arts",
    "world": "interior_design",
    "subcategory": "color_palettes",
    "entity": "Color Palettes Entry 45",
    "entity_type": "Concept",
    "features": {
      "visual": {
        "signature": "Recognition Cue"
      },
      "semantic": {
        "context": "Domain Knowledge"
      }
    },
    "dimensions": {
      "Category": "Interior Design",
      "Signature": "Primary Fingerprint"
    },
    "confusions": [
      "Neighboring Concept"
    ],
    "difficulty": 1,
    "confidence": {
      "signature": "High"
    }
  },
  {
    "observation_id": "creative_arts_interior_design_color_palettes_0046",
    "universe": "creative_arts",
    "world": "interior_design",
    "subcategory": "color_palettes",
    "entity": "Color Palettes Entry 46",
    "entity_type": "Concept",
    "features": {
      "visual": {
        "signature": "Recognition Cue"
      },
      "semantic": {
        "context": "Domain Knowledge"
      }
    },
    "dimensions": {
      "Category": "Interior Design",
      "Signature": "Primary Fingerprint"
    },
    "confusions": [
      "Neighboring Concept"
    ],
    "difficulty": 2,
    "confidence": {
      "signature": "High"
    }
  },
  {
    "observation_id": "creative_arts_interior_design_color_palettes_0047",
    "universe": "creative_arts",
    "world": "interior_design",
    "subcategory": "color_palettes",
    "entity": "Color Palettes Entry 47",
    "entity_type": "Concept",
    "features": {
      "visual": {
        "signature": "Recognition Cue"
      },
      "semantic": {
        "context": "Domain Knowledge"
      }
    },
    "dimensions": {
      "Category": "Interior Design",
      "Signature": "Primary Fingerprint"
    },
    "confusions": [
      "Neighboring Concept"
    ],
    "difficulty": 3,
    "confidence": {
      "signature": "High"
    }
  },
  {
    "observation_id": "creative_arts_interior_design_color_palettes_0048",
    "universe": "creative_arts",
    "world": "interior_design",
    "subcategory": "color_palettes",
    "entity": "Color Palettes Entry 48",
    "entity_type": "Concept",
    "features": {
      "visual": {
        "signature": "Recognition Cue"
      },
      "semantic": {
        "context": "Domain Knowledge"
      }
    },
    "dimensions": {
      "Category": "Interior Design",
      "Signature": "Primary Fingerprint"
    },
    "confusions": [
      "Neighboring Concept"
    ],
    "difficulty": 4,
    "confidence": {
      "signature": "High"
    }
  },
  {
    "observation_id": "creative_arts_interior_design_color_palettes_0049",
    "universe": "creative_arts",
    "world": "interior_design",
    "subcategory": "color_palettes",
    "entity": "Color Palettes Entry 49",
    "entity_type": "Concept",
    "features": {
      "visual": {
        "signature": "Recognition Cue"
      },
      "semantic": {
        "context": "Domain Knowledge"
      }
    },
    "dimensions": {
      "Category": "Interior Design",
      "Signature": "Primary Fingerprint"
    },
    "confusions": [
      "Neighboring Concept"
    ],
    "difficulty": 5,
    "confidence": {
      "signature": "High"
    }
  },
  {
    "observation_id": "creative_arts_interior_design_color_palettes_0050",
    "universe": "creative_arts",
    "world": "interior_design",
    "subcategory": "color_palettes",
    "entity": "Color Palettes Entry 50",
    "entity_type": "Concept",
    "features": {
      "visual": {
        "signature": "Recognition Cue"
      },
      "semantic": {
        "context": "Domain Knowledge"
      }
    },
    "dimensions": {
      "Category": "Interior Design",
      "Signature": "Primary Fingerprint"
    },
    "confusions": [
      "Neighboring Concept"
    ],
    "difficulty": 1,
    "confidence": {
      "signature": "High"
    }
  },
  {
    "observation_id": "creative_arts_interior_design_color_palettes_0051",
    "universe": "creative_arts",
    "world": "interior_design",
    "subcategory": "color_palettes",
    "entity": "Color Palettes Entry 51",
    "entity_type": "Concept",
    "features": {
      "visual": {
        "signature": "Recognition Cue"
      },
      "semantic": {
        "context": "Domain Knowledge"
      }
    },
    "dimensions": {
      "Category": "Interior Design",
      "Signature": "Primary Fingerprint"
    },
    "confusions": [
      "Neighboring Concept"
    ],
    "difficulty": 2,
    "confidence": {
      "signature": "High"
    }
  },
  {
    "observation_id": "creative_arts_interior_design_color_palettes_0052",
    "universe": "creative_arts",
    "world": "interior_design",
    "subcategory": "color_palettes",
    "entity": "Color Palettes Entry 52",
    "entity_type": "Concept",
    "features": {
      "visual": {
        "signature": "Recognition Cue"
      },
      "semantic": {
        "context": "Domain Knowledge"
      }
    },
    "dimensions": {
      "Category": "Interior Design",
      "Signature": "Primary Fingerprint"
    },
    "confusions": [
      "Neighboring Concept"
    ],
    "difficulty": 3,
    "confidence": {
      "signature": "High"
    }
  },
  {
    "observation_id": "creative_arts_interior_design_color_palettes_0053",
    "universe": "creative_arts",
    "world": "interior_design",
    "subcategory": "color_palettes",
    "entity": "Color Palettes Entry 53",
    "entity_type": "Concept",
    "features": {
      "visual": {
        "signature": "Recognition Cue"
      },
      "semantic": {
        "context": "Domain Knowledge"
      }
    },
    "dimensions": {
      "Category": "Interior Design",
      "Signature": "Primary Fingerprint"
    },
    "confusions": [
      "Neighboring Concept"
    ],
    "difficulty": 4,
    "confidence": {
      "signature": "High"
    }
  },
  {
    "observation_id": "creative_arts_interior_design_color_palettes_0054",
    "universe": "creative_arts",
    "world": "interior_design",
    "subcategory": "color_palettes",
    "entity": "Color Palettes Entry 54",
    "entity_type": "Concept",
    "features": {
      "visual": {
        "signature": "Recognition Cue"
      },
      "semantic": {
        "context": "Domain Knowledge"
      }
    },
    "dimensions": {
      "Category": "Interior Design",
      "Signature": "Primary Fingerprint"
    },
    "confusions": [
      "Neighboring Concept"
    ],
    "difficulty": 5,
    "confidence": {
      "signature": "High"
    }
  },
  {
    "observation_id": "creative_arts_interior_design_color_palettes_0055",
    "universe": "creative_arts",
    "world": "interior_design",
    "subcategory": "color_palettes",
    "entity": "Color Palettes Entry 55",
    "entity_type": "Concept",
    "features": {
      "visual": {
        "signature": "Recognition Cue"
      },
      "semantic": {
        "context": "Domain Knowledge"
      }
    },
    "dimensions": {
      "Category": "Interior Design",
      "Signature": "Primary Fingerprint"
    },
    "confusions": [
      "Neighboring Concept"
    ],
    "difficulty": 1,
    "confidence": {
      "signature": "High"
    }
  },
  {
    "observation_id": "creative_arts_interior_design_color_palettes_0056",
    "universe": "creative_arts",
    "world": "interior_design",
    "subcategory": "color_palettes",
    "entity": "Color Palettes Entry 56",
    "entity_type": "Concept",
    "features": {
      "visual": {
        "signature": "Recognition Cue"
      },
      "semantic": {
        "context": "Domain Knowledge"
      }
    },
    "dimensions": {
      "Category": "Interior Design",
      "Signature": "Primary Fingerprint"
    },
    "confusions": [
      "Neighboring Concept"
    ],
    "difficulty": 2,
    "confidence": {
      "signature": "High"
    }
  },
  {
    "observation_id": "creative_arts_interior_design_color_palettes_0057",
    "universe": "creative_arts",
    "world": "interior_design",
    "subcategory": "color_palettes",
    "entity": "Color Palettes Entry 57",
    "entity_type": "Concept",
    "features": {
      "visual": {
        "signature": "Recognition Cue"
      },
      "semantic": {
        "context": "Domain Knowledge"
      }
    },
    "dimensions": {
      "Category": "Interior Design",
      "Signature": "Primary Fingerprint"
    },
    "confusions": [
      "Neighboring Concept"
    ],
    "difficulty": 3,
    "confidence": {
      "signature": "High"
    }
  },
  {
    "observation_id": "creative_arts_interior_design_color_palettes_0058",
    "universe": "creative_arts",
    "world": "interior_design",
    "subcategory": "color_palettes",
    "entity": "Color Palettes Entry 58",
    "entity_type": "Concept",
    "features": {
      "visual": {
        "signature": "Recognition Cue"
      },
      "semantic": {
        "context": "Domain Knowledge"
      }
    },
    "dimensions": {
      "Category": "Interior Design",
      "Signature": "Primary Fingerprint"
    },
    "confusions": [
      "Neighboring Concept"
    ],
    "difficulty": 4,
    "confidence": {
      "signature": "High"
    }
  },
  {
    "observation_id": "creative_arts_interior_design_color_palettes_0059",
    "universe": "creative_arts",
    "world": "interior_design",
    "subcategory": "color_palettes",
    "entity": "Color Palettes Entry 59",
    "entity_type": "Concept",
    "features": {
      "visual": {
        "signature": "Recognition Cue"
      },
      "semantic": {
        "context": "Domain Knowledge"
      }
    },
    "dimensions": {
      "Category": "Interior Design",
      "Signature": "Primary Fingerprint"
    },
    "confusions": [
      "Neighboring Concept"
    ],
    "difficulty": 5,
    "confidence": {
      "signature": "High"
    }
  },
  {
    "observation_id": "creative_arts_interior_design_color_palettes_0060",
    "universe": "creative_arts",
    "world": "interior_design",
    "subcategory": "color_palettes",
    "entity": "Color Palettes Entry 60",
    "entity_type": "Concept",
    "features": {
      "visual": {
        "signature": "Recognition Cue"
      },
      "semantic": {
        "context": "Domain Knowledge"
      }
    },
    "dimensions": {
      "Category": "Interior Design",
      "Signature": "Primary Fingerprint"
    },
    "confusions": [
      "Neighboring Concept"
    ],
    "difficulty": 1,
    "confidence": {
      "signature": "High"
    }
  },
  {
    "observation_id": "creative_arts_interior_design_color_palettes_0061",
    "universe": "creative_arts",
    "world": "interior_design",
    "subcategory": "color_palettes",
    "entity": "Color Palettes Entry 61",
    "entity_type": "Concept",
    "features": {
      "visual": {
        "signature": "Recognition Cue"
      },
      "semantic": {
        "context": "Domain Knowledge"
      }
    },
    "dimensions": {
      "Category": "Interior Design",
      "Signature": "Primary Fingerprint"
    },
    "confusions": [
      "Neighboring Concept"
    ],
    "difficulty": 2,
    "confidence": {
      "signature": "High"
    }
  },
  {
    "observation_id": "creative_arts_interior_design_color_palettes_0062",
    "universe": "creative_arts",
    "world": "interior_design",
    "subcategory": "color_palettes",
    "entity": "Color Palettes Entry 62",
    "entity_type": "Concept",
    "features": {
      "visual": {
        "signature": "Recognition Cue"
      },
      "semantic": {
        "context": "Domain Knowledge"
      }
    },
    "dimensions": {
      "Category": "Interior Design",
      "Signature": "Primary Fingerprint"
    },
    "confusions": [
      "Neighboring Concept"
    ],
    "difficulty": 3,
    "confidence": {
      "signature": "High"
    }
  },
  {
    "observation_id": "creative_arts_interior_design_color_palettes_0063",
    "universe": "creative_arts",
    "world": "interior_design",
    "subcategory": "color_palettes",
    "entity": "Color Palettes Entry 63",
    "entity_type": "Concept",
    "features": {
      "visual": {
        "signature": "Recognition Cue"
      },
      "semantic": {
        "context": "Domain Knowledge"
      }
    },
    "dimensions": {
      "Category": "Interior Design",
      "Signature": "Primary Fingerprint"
    },
    "confusions": [
      "Neighboring Concept"
    ],
    "difficulty": 4,
    "confidence": {
      "signature": "High"
    }
  },
  {
    "observation_id": "creative_arts_interior_design_color_palettes_0064",
    "universe": "creative_arts",
    "world": "interior_design",
    "subcategory": "color_palettes",
    "entity": "Color Palettes Entry 64",
    "entity_type": "Concept",
    "features": {
      "visual": {
        "signature": "Recognition Cue"
      },
      "semantic": {
        "context": "Domain Knowledge"
      }
    },
    "dimensions": {
      "Category": "Interior Design",
      "Signature": "Primary Fingerprint"
    },
    "confusions": [
      "Neighboring Concept"
    ],
    "difficulty": 5,
    "confidence": {
      "signature": "High"
    }
  },
  {
    "observation_id": "creative_arts_interior_design_color_palettes_0065",
    "universe": "creative_arts",
    "world": "interior_design",
    "subcategory": "color_palettes",
    "entity": "Color Palettes Entry 65",
    "entity_type": "Concept",
    "features": {
      "visual": {
        "signature": "Recognition Cue"
      },
      "semantic": {
        "context": "Domain Knowledge"
      }
    },
    "dimensions": {
      "Category": "Interior Design",
      "Signature": "Primary Fingerprint"
    },
    "confusions": [
      "Neighboring Concept"
    ],
    "difficulty": 1,
    "confidence": {
      "signature": "High"
    }
  },
  {
    "observation_id": "creative_arts_interior_design_color_palettes_0066",
    "universe": "creative_arts",
    "world": "interior_design",
    "subcategory": "color_palettes",
    "entity": "Color Palettes Entry 66",
    "entity_type": "Concept",
    "features": {
      "visual": {
        "signature": "Recognition Cue"
      },
      "semantic": {
        "context": "Domain Knowledge"
      }
    },
    "dimensions": {
      "Category": "Interior Design",
      "Signature": "Primary Fingerprint"
    },
    "confusions": [
      "Neighboring Concept"
    ],
    "difficulty": 2,
    "confidence": {
      "signature": "High"
    }
  },
  {
    "observation_id": "creative_arts_interior_design_color_palettes_0067",
    "universe": "creative_arts",
    "world": "interior_design",
    "subcategory": "color_palettes",
    "entity": "Color Palettes Entry 67",
    "entity_type": "Concept",
    "features": {
      "visual": {
        "signature": "Recognition Cue"
      },
      "semantic": {
        "context": "Domain Knowledge"
      }
    },
    "dimensions": {
      "Category": "Interior Design",
      "Signature": "Primary Fingerprint"
    },
    "confusions": [
      "Neighboring Concept"
    ],
    "difficulty": 3,
    "confidence": {
      "signature": "High"
    }
  },
  {
    "observation_id": "creative_arts_interior_design_color_palettes_0068",
    "universe": "creative_arts",
    "world": "interior_design",
    "subcategory": "color_palettes",
    "entity": "Color Palettes Entry 68",
    "entity_type": "Concept",
    "features": {
      "visual": {
        "signature": "Recognition Cue"
      },
      "semantic": {
        "context": "Domain Knowledge"
      }
    },
    "dimensions": {
      "Category": "Interior Design",
      "Signature": "Primary Fingerprint"
    },
    "confusions": [
      "Neighboring Concept"
    ],
    "difficulty": 4,
    "confidence": {
      "signature": "High"
    }
  },
  {
    "observation_id": "creative_arts_interior_design_color_palettes_0069",
    "universe": "creative_arts",
    "world": "interior_design",
    "subcategory": "color_palettes",
    "entity": "Color Palettes Entry 69",
    "entity_type": "Concept",
    "features": {
      "visual": {
        "signature": "Recognition Cue"
      },
      "semantic": {
        "context": "Domain Knowledge"
      }
    },
    "dimensions": {
      "Category": "Interior Design",
      "Signature": "Primary Fingerprint"
    },
    "confusions": [
      "Neighboring Concept"
    ],
    "difficulty": 5,
    "confidence": {
      "signature": "High"
    }
  },
  {
    "observation_id": "creative_arts_interior_design_color_palettes_0070",
    "universe": "creative_arts",
    "world": "interior_design",
    "subcategory": "color_palettes",
    "entity": "Color Palettes Entry 70",
    "entity_type": "Concept",
    "features": {
      "visual": {
        "signature": "Recognition Cue"
      },
      "semantic": {
        "context": "Domain Knowledge"
      }
    },
    "dimensions": {
      "Category": "Interior Design",
      "Signature": "Primary Fingerprint"
    },
    "confusions": [
      "Neighboring Concept"
    ],
    "difficulty": 1,
    "confidence": {
      "signature": "High"
    }
  },
  {
    "observation_id": "creative_arts_interior_design_color_palettes_0071",
    "universe": "creative_arts",
    "world": "interior_design",
    "subcategory": "color_palettes",
    "entity": "Color Palettes Entry 71",
    "entity_type": "Concept",
    "features": {
      "visual": {
        "signature": "Recognition Cue"
      },
      "semantic": {
        "context": "Domain Knowledge"
      }
    },
    "dimensions": {
      "Category": "Interior Design",
      "Signature": "Primary Fingerprint"
    },
    "confusions": [
      "Neighboring Concept"
    ],
    "difficulty": 2,
    "confidence": {
      "signature": "High"
    }
  },
  {
    "observation_id": "creative_arts_interior_design_color_palettes_0072",
    "universe": "creative_arts",
    "world": "interior_design",
    "subcategory": "color_palettes",
    "entity": "Color Palettes Entry 72",
    "entity_type": "Concept",
    "features": {
      "visual": {
        "signature": "Recognition Cue"
      },
      "semantic": {
        "context": "Domain Knowledge"
      }
    },
    "dimensions": {
      "Category": "Interior Design",
      "Signature": "Primary Fingerprint"
    },
    "confusions": [
      "Neighboring Concept"
    ],
    "difficulty": 3,
    "confidence": {
      "signature": "High"
    }
  },
  {
    "observation_id": "creative_arts_interior_design_color_palettes_0073",
    "universe": "creative_arts",
    "world": "interior_design",
    "subcategory": "color_palettes",
    "entity": "Color Palettes Entry 73",
    "entity_type": "Concept",
    "features": {
      "visual": {
        "signature": "Recognition Cue"
      },
      "semantic": {
        "context": "Domain Knowledge"
      }
    },
    "dimensions": {
      "Category": "Interior Design",
      "Signature": "Primary Fingerprint"
    },
    "confusions": [
      "Neighboring Concept"
    ],
    "difficulty": 4,
    "confidence": {
      "signature": "High"
    }
  },
  {
    "observation_id": "creative_arts_interior_design_color_palettes_0074",
    "universe": "creative_arts",
    "world": "interior_design",
    "subcategory": "color_palettes",
    "entity": "Color Palettes Entry 74",
    "entity_type": "Concept",
    "features": {
      "visual": {
        "signature": "Recognition Cue"
      },
      "semantic": {
        "context": "Domain Knowledge"
      }
    },
    "dimensions": {
      "Category": "Interior Design",
      "Signature": "Primary Fingerprint"
    },
    "confusions": [
      "Neighboring Concept"
    ],
    "difficulty": 5,
    "confidence": {
      "signature": "High"
    }
  },
  {
    "observation_id": "creative_arts_interior_design_color_palettes_0075",
    "universe": "creative_arts",
    "world": "interior_design",
    "subcategory": "color_palettes",
    "entity": "Color Palettes Entry 75",
    "entity_type": "Concept",
    "features": {
      "visual": {
        "signature": "Recognition Cue"
      },
      "semantic": {
        "context": "Domain Knowledge"
      }
    },
    "dimensions": {
      "Category": "Interior Design",
      "Signature": "Primary Fingerprint"
    },
    "confusions": [
      "Neighboring Concept"
    ],
    "difficulty": 1,
    "confidence": {
      "signature": "High"
    }
  },
  {
    "observation_id": "creative_arts_interior_design_color_palettes_0076",
    "universe": "creative_arts",
    "world": "interior_design",
    "subcategory": "color_palettes",
    "entity": "Color Palettes Entry 76",
    "entity_type": "Concept",
    "features": {
      "visual": {
        "signature": "Recognition Cue"
      },
      "semantic": {
        "context": "Domain Knowledge"
      }
    },
    "dimensions": {
      "Category": "Interior Design",
      "Signature": "Primary Fingerprint"
    },
    "confusions": [
      "Neighboring Concept"
    ],
    "difficulty": 2,
    "confidence": {
      "signature": "High"
    }
  },
  {
    "observation_id": "creative_arts_interior_design_color_palettes_0077",
    "universe": "creative_arts",
    "world": "interior_design",
    "subcategory": "color_palettes",
    "entity": "Color Palettes Entry 77",
    "entity_type": "Concept",
    "features": {
      "visual": {
        "signature": "Recognition Cue"
      },
      "semantic": {
        "context": "Domain Knowledge"
      }
    },
    "dimensions": {
      "Category": "Interior Design",
      "Signature": "Primary Fingerprint"
    },
    "confusions": [
      "Neighboring Concept"
    ],
    "difficulty": 3,
    "confidence": {
      "signature": "High"
    }
  },
  {
    "observation_id": "creative_arts_interior_design_color_palettes_0078",
    "universe": "creative_arts",
    "world": "interior_design",
    "subcategory": "color_palettes",
    "entity": "Color Palettes Entry 78",
    "entity_type": "Concept",
    "features": {
      "visual": {
        "signature": "Recognition Cue"
      },
      "semantic": {
        "context": "Domain Knowledge"
      }
    },
    "dimensions": {
      "Category": "Interior Design",
      "Signature": "Primary Fingerprint"
    },
    "confusions": [
      "Neighboring Concept"
    ],
    "difficulty": 4,
    "confidence": {
      "signature": "High"
    }
  },
  {
    "observation_id": "creative_arts_interior_design_color_palettes_0079",
    "universe": "creative_arts",
    "world": "interior_design",
    "subcategory": "color_palettes",
    "entity": "Color Palettes Entry 79",
    "entity_type": "Concept",
    "features": {
      "visual": {
        "signature": "Recognition Cue"
      },
      "semantic": {
        "context": "Domain Knowledge"
      }
    },
    "dimensions": {
      "Category": "Interior Design",
      "Signature": "Primary Fingerprint"
    },
    "confusions": [
      "Neighboring Concept"
    ],
    "difficulty": 5,
    "confidence": {
      "signature": "High"
    }
  },
  {
    "observation_id": "creative_arts_interior_design_color_palettes_0080",
    "universe": "creative_arts",
    "world": "interior_design",
    "subcategory": "color_palettes",
    "entity": "Color Palettes Entry 80",
    "entity_type": "Concept",
    "features": {
      "visual": {
        "signature": "Recognition Cue"
      },
      "semantic": {
        "context": "Domain Knowledge"
      }
    },
    "dimensions": {
      "Category": "Interior Design",
      "Signature": "Primary Fingerprint"
    },
    "confusions": [
      "Neighboring Concept"
    ],
    "difficulty": 1,
    "confidence": {
      "signature": "High"
    }
  },
  {
    "observation_id": "creative_arts_interior_design_color_palettes_0081",
    "universe": "creative_arts",
    "world": "interior_design",
    "subcategory": "color_palettes",
    "entity": "Color Palettes Entry 81",
    "entity_type": "Concept",
    "features": {
      "visual": {
        "signature": "Recognition Cue"
      },
      "semantic": {
        "context": "Domain Knowledge"
      }
    },
    "dimensions": {
      "Category": "Interior Design",
      "Signature": "Primary Fingerprint"
    },
    "confusions": [
      "Neighboring Concept"
    ],
    "difficulty": 2,
    "confidence": {
      "signature": "High"
    }
  },
  {
    "observation_id": "creative_arts_interior_design_color_palettes_0082",
    "universe": "creative_arts",
    "world": "interior_design",
    "subcategory": "color_palettes",
    "entity": "Color Palettes Entry 82",
    "entity_type": "Concept",
    "features": {
      "visual": {
        "signature": "Recognition Cue"
      },
      "semantic": {
        "context": "Domain Knowledge"
      }
    },
    "dimensions": {
      "Category": "Interior Design",
      "Signature": "Primary Fingerprint"
    },
    "confusions": [
      "Neighboring Concept"
    ],
    "difficulty": 3,
    "confidence": {
      "signature": "High"
    }
  },
  {
    "observation_id": "creative_arts_interior_design_color_palettes_0083",
    "universe": "creative_arts",
    "world": "interior_design",
    "subcategory": "color_palettes",
    "entity": "Color Palettes Entry 83",
    "entity_type": "Concept",
    "features": {
      "visual": {
        "signature": "Recognition Cue"
      },
      "semantic": {
        "context": "Domain Knowledge"
      }
    },
    "dimensions": {
      "Category": "Interior Design",
      "Signature": "Primary Fingerprint"
    },
    "confusions": [
      "Neighboring Concept"
    ],
    "difficulty": 4,
    "confidence": {
      "signature": "High"
    }
  },
  {
    "observation_id": "creative_arts_interior_design_color_palettes_0084",
    "universe": "creative_arts",
    "world": "interior_design",
    "subcategory": "color_palettes",
    "entity": "Color Palettes Entry 84",
    "entity_type": "Concept",
    "features": {
      "visual": {
        "signature": "Recognition Cue"
      },
      "semantic": {
        "context": "Domain Knowledge"
      }
    },
    "dimensions": {
      "Category": "Interior Design",
      "Signature": "Primary Fingerprint"
    },
    "confusions": [
      "Neighboring Concept"
    ],
    "difficulty": 5,
    "confidence": {
      "signature": "High"
    }
  },
  {
    "observation_id": "creative_arts_interior_design_color_palettes_0085",
    "universe": "creative_arts",
    "world": "interior_design",
    "subcategory": "color_palettes",
    "entity": "Color Palettes Entry 85",
    "entity_type": "Concept",
    "features": {
      "visual": {
        "signature": "Recognition Cue"
      },
      "semantic": {
        "context": "Domain Knowledge"
      }
    },
    "dimensions": {
      "Category": "Interior Design",
      "Signature": "Primary Fingerprint"
    },
    "confusions": [
      "Neighboring Concept"
    ],
    "difficulty": 1,
    "confidence": {
      "signature": "High"
    }
  },
  {
    "observation_id": "creative_arts_interior_design_color_palettes_0086",
    "universe": "creative_arts",
    "world": "interior_design",
    "subcategory": "color_palettes",
    "entity": "Color Palettes Entry 86",
    "entity_type": "Concept",
    "features": {
      "visual": {
        "signature": "Recognition Cue"
      },
      "semantic": {
        "context": "Domain Knowledge"
      }
    },
    "dimensions": {
      "Category": "Interior Design",
      "Signature": "Primary Fingerprint"
    },
    "confusions": [
      "Neighboring Concept"
    ],
    "difficulty": 2,
    "confidence": {
      "signature": "High"
    }
  },
  {
    "observation_id": "creative_arts_interior_design_color_palettes_0087",
    "universe": "creative_arts",
    "world": "interior_design",
    "subcategory": "color_palettes",
    "entity": "Color Palettes Entry 87",
    "entity_type": "Concept",
    "features": {
      "visual": {
        "signature": "Recognition Cue"
      },
      "semantic": {
        "context": "Domain Knowledge"
      }
    },
    "dimensions": {
      "Category": "Interior Design",
      "Signature": "Primary Fingerprint"
    },
    "confusions": [
      "Neighboring Concept"
    ],
    "difficulty": 3,
    "confidence": {
      "signature": "High"
    }
  },
  {
    "observation_id": "creative_arts_interior_design_color_palettes_0088",
    "universe": "creative_arts",
    "world": "interior_design",
    "subcategory": "color_palettes",
    "entity": "Color Palettes Entry 88",
    "entity_type": "Concept",
    "features": {
      "visual": {
        "signature": "Recognition Cue"
      },
      "semantic": {
        "context": "Domain Knowledge"
      }
    },
    "dimensions": {
      "Category": "Interior Design",
      "Signature": "Primary Fingerprint"
    },
    "confusions": [
      "Neighboring Concept"
    ],
    "difficulty": 4,
    "confidence": {
      "signature": "High"
    }
  },
  {
    "observation_id": "creative_arts_interior_design_color_palettes_0089",
    "universe": "creative_arts",
    "world": "interior_design",
    "subcategory": "color_palettes",
    "entity": "Color Palettes Entry 89",
    "entity_type": "Concept",
    "features": {
      "visual": {
        "signature": "Recognition Cue"
      },
      "semantic": {
        "context": "Domain Knowledge"
      }
    },
    "dimensions": {
      "Category": "Interior Design",
      "Signature": "Primary Fingerprint"
    },
    "confusions": [
      "Neighboring Concept"
    ],
    "difficulty": 5,
    "confidence": {
      "signature": "High"
    }
  },
  {
    "observation_id": "creative_arts_interior_design_color_palettes_0090",
    "universe": "creative_arts",
    "world": "interior_design",
    "subcategory": "color_palettes",
    "entity": "Color Palettes Entry 90",
    "entity_type": "Concept",
    "features": {
      "visual": {
        "signature": "Recognition Cue"
      },
      "semantic": {
        "context": "Domain Knowledge"
      }
    },
    "dimensions": {
      "Category": "Interior Design",
      "Signature": "Primary Fingerprint"
    },
    "confusions": [
      "Neighboring Concept"
    ],
    "difficulty": 1,
    "confidence": {
      "signature": "High"
    }
  },
  {
    "observation_id": "creative_arts_interior_design_color_palettes_0091",
    "universe": "creative_arts",
    "world": "interior_design",
    "subcategory": "color_palettes",
    "entity": "Color Palettes Entry 91",
    "entity_type": "Concept",
    "features": {
      "visual": {
        "signature": "Recognition Cue"
      },
      "semantic": {
        "context": "Domain Knowledge"
      }
    },
    "dimensions": {
      "Category": "Interior Design",
      "Signature": "Primary Fingerprint"
    },
    "confusions": [
      "Neighboring Concept"
    ],
    "difficulty": 2,
    "confidence": {
      "signature": "High"
    }
  },
  {
    "observation_id": "creative_arts_interior_design_color_palettes_0092",
    "universe": "creative_arts",
    "world": "interior_design",
    "subcategory": "color_palettes",
    "entity": "Color Palettes Entry 92",
    "entity_type": "Concept",
    "features": {
      "visual": {
        "signature": "Recognition Cue"
      },
      "semantic": {
        "context": "Domain Knowledge"
      }
    },
    "dimensions": {
      "Category": "Interior Design",
      "Signature": "Primary Fingerprint"
    },
    "confusions": [
      "Neighboring Concept"
    ],
    "difficulty": 3,
    "confidence": {
      "signature": "High"
    }
  },
  {
    "observation_id": "creative_arts_interior_design_color_palettes_0093",
    "universe": "creative_arts",
    "world": "interior_design",
    "subcategory": "color_palettes",
    "entity": "Color Palettes Entry 93",
    "entity_type": "Concept",
    "features": {
      "visual": {
        "signature": "Recognition Cue"
      },
      "semantic": {
        "context": "Domain Knowledge"
      }
    },
    "dimensions": {
      "Category": "Interior Design",
      "Signature": "Primary Fingerprint"
    },
    "confusions": [
      "Neighboring Concept"
    ],
    "difficulty": 4,
    "confidence": {
      "signature": "High"
    }
  },
  {
    "observation_id": "creative_arts_interior_design_color_palettes_0094",
    "universe": "creative_arts",
    "world": "interior_design",
    "subcategory": "color_palettes",
    "entity": "Color Palettes Entry 94",
    "entity_type": "Concept",
    "features": {
      "visual": {
        "signature": "Recognition Cue"
      },
      "semantic": {
        "context": "Domain Knowledge"
      }
    },
    "dimensions": {
      "Category": "Interior Design",
      "Signature": "Primary Fingerprint"
    },
    "confusions": [
      "Neighboring Concept"
    ],
    "difficulty": 5,
    "confidence": {
      "signature": "High"
    }
  },
  {
    "observation_id": "creative_arts_interior_design_color_palettes_0095",
    "universe": "creative_arts",
    "world": "interior_design",
    "subcategory": "color_palettes",
    "entity": "Color Palettes Entry 95",
    "entity_type": "Concept",
    "features": {
      "visual": {
        "signature": "Recognition Cue"
      },
      "semantic": {
        "context": "Domain Knowledge"
      }
    },
    "dimensions": {
      "Category": "Interior Design",
      "Signature": "Primary Fingerprint"
    },
    "confusions": [
      "Neighboring Concept"
    ],
    "difficulty": 1,
    "confidence": {
      "signature": "High"
    }
  },
  {
    "observation_id": "creative_arts_interior_design_color_palettes_0096",
    "universe": "creative_arts",
    "world": "interior_design",
    "subcategory": "color_palettes",
    "entity": "Color Palettes Entry 96",
    "entity_type": "Concept",
    "features": {
      "visual": {
        "signature": "Recognition Cue"
      },
      "semantic": {
        "context": "Domain Knowledge"
      }
    },
    "dimensions": {
      "Category": "Interior Design",
      "Signature": "Primary Fingerprint"
    },
    "confusions": [
      "Neighboring Concept"
    ],
    "difficulty": 2,
    "confidence": {
      "signature": "High"
    }
  },
  {
    "observation_id": "creative_arts_interior_design_color_palettes_0097",
    "universe": "creative_arts",
    "world": "interior_design",
    "subcategory": "color_palettes",
    "entity": "Color Palettes Entry 97",
    "entity_type": "Concept",
    "features": {
      "visual": {
        "signature": "Recognition Cue"
      },
      "semantic": {
        "context": "Domain Knowledge"
      }
    },
    "dimensions": {
      "Category": "Interior Design",
      "Signature": "Primary Fingerprint"
    },
    "confusions": [
      "Neighboring Concept"
    ],
    "difficulty": 3,
    "confidence": {
      "signature": "High"
    }
  },
  {
    "observation_id": "creative_arts_interior_design_color_palettes_0098",
    "universe": "creative_arts",
    "world": "interior_design",
    "subcategory": "color_palettes",
    "entity": "Color Palettes Entry 98",
    "entity_type": "Concept",
    "features": {
      "visual": {
        "signature": "Recognition Cue"
      },
      "semantic": {
        "context": "Domain Knowledge"
      }
    },
    "dimensions": {
      "Category": "Interior Design",
      "Signature": "Primary Fingerprint"
    },
    "confusions": [
      "Neighboring Concept"
    ],
    "difficulty": 4,
    "confidence": {
      "signature": "High"
    }
  },
  {
    "observation_id": "creative_arts_interior_design_color_palettes_0099",
    "universe": "creative_arts",
    "world": "interior_design",
    "subcategory": "color_palettes",
    "entity": "Color Palettes Entry 99",
    "entity_type": "Concept",
    "features": {
      "visual": {
        "signature": "Recognition Cue"
      },
      "semantic": {
        "context": "Domain Knowledge"
      }
    },
    "dimensions": {
      "Category": "Interior Design",
      "Signature": "Primary Fingerprint"
    },
    "confusions": [
      "Neighboring Concept"
    ],
    "difficulty": 5,
    "confidence": {
      "signature": "High"
    }
  },
  {
    "observation_id": "creative_arts_interior_design_color_palettes_0100",
    "universe": "creative_arts",
    "world": "interior_design",
    "subcategory": "color_palettes",
    "entity": "Color Palettes Entry 100",
    "entity_type": "Concept",
    "features": {
      "visual": {
        "signature": "Recognition Cue"
      },
      "semantic": {
        "context": "Domain Knowledge"
      }
    },
    "dimensions": {
      "Category": "Interior Design",
      "Signature": "Primary Fingerprint"
    },
    "confusions": [
      "Neighboring Concept"
    ],
    "difficulty": 1,
    "confidence": {
      "signature": "High"
    }
  }
]