{
    "id": "arctic_005",
    "universe": "frontier",
    "world": "arctic",
    "type": "rapid_classification",
    "difficulty": 1,
    "rewards": {
        "xp": 10,
        "currency": 0
    },
    "rules": {
        "time_limit": 5.0,
        "attempts": 1,
        "legacy_flash": "POLAR",
        "legacy_prompt": "Sun not setting for months during summer near the poles.",
        "correct_answer": "Midnight Sun",
        "wrong_answers": [
            "Solstice",
            "Equinox",
            "Polar Day"
        ]
    },
    "presentation": {
        "title": "Identify:",
        "visual_theme_override": null
    }
}