[
  {
    "observation_id": "creative_arts_animation_timing_0001",
    "universe": "creative_arts",
    "world": "animation",
    "subcategory": "timing",
    "entity": "Timing Concept 1",
    "entity_type": "Concept",
    "features": {
      "visual": {
        "signature": "Recognition Cue"
      },
      "semantic": {
        "context": "Domain Knowledge"
      }
    },
    "dimensions": {
      "Category": "Animation",
      "Signature": "Primary Fingerprint"
    },
    "confusions": [
      "Neighboring Concept"
    ],
    "difficulty": 2,
    "confidence": {
      "signature": "High"
    }
  },
  {
    "observation_id": "creative_arts_animation_timing_0002",
    "universe": "creative_arts",
    "world": "animation",
    "subcategory": "timing",
    "entity": "Timing Concept 2",
    "entity_type": "Concept",
    "features": {
      "visual": {
        "signature": "Recognition Cue"
      },
      "semantic": {
        "context": "Domain Knowledge"
      }
    },
    "dimensions": {
      "Category": "Animation",
      "Signature": "Primary Fingerprint"
    },
    "confusions": [
      "Neighboring Concept"
    ],
    "difficulty": 3,
    "confidence": {
      "signature": "High"
    }
  },
  {
    "observation_id": "creative_arts_animation_timing_0003",
    "universe": "creative_arts",
    "world": "animation",
    "subcategory": "timing",
    "entity": "Timing Concept 3",
    "entity_type": "Concept",
    "features": {
      "visual": {
        "signature": "Recognition Cue"
      },
      "semantic": {
        "context": "Domain Knowledge"
      }
    },
    "dimensions": {
      "Category": "Animation",
      "Signature": "Primary Fingerprint"
    },
    "confusions": [
      "Neighboring Concept"
    ],
    "difficulty": 4,
    "confidence": {
      "signature": "High"
    }
  },
  {
    "observation_id": "creative_arts_animation_timing_0004",
    "universe": "creative_arts",
    "world": "animation",
    "subcategory": "timing",
    "entity": "Timing Concept 4",
    "entity_type": "Concept",
    "features": {
      "visual": {
        "signature": "Recognition Cue"
      },
      "semantic": {
        "context": "Domain Knowledge"
      }
    },
    "dimensions": {
      "Category": "Animation",
      "Signature": "Primary Fingerprint"
    },
    "confusions": [
      "Neighboring Concept"
    ],
    "difficulty": 5,
    "confidence": {
      "signature": "High"
    }
  },
  {
    "observation_id": "creative_arts_animation_timing_0005",
    "universe": "creative_arts",
    "world": "animation",
    "subcategory": "timing",
    "entity": "Timing Concept 5",
    "entity_type": "Concept",
    "features": {
      "visual": {
        "signature": "Recognition Cue"
      },
      "semantic": {
        "context": "Domain Knowledge"
      }
    },
    "dimensions": {
      "Category": "Animation",
      "Signature": "Primary Fingerprint"
    },
    "confusions": [
      "Neighboring Concept"
    ],
    "difficulty": 1,
    "confidence": {
      "signature": "High"
    }
  },
  {
    "observation_id": "creative_arts_animation_timing_0006",
    "universe": "creative_arts",
    "world": "animation",
    "subcategory": "timing",
    "entity": "Timing Concept 6",
    "entity_type": "Concept",
    "features": {
      "visual": {
        "signature": "Recognition Cue"
      },
      "semantic": {
        "context": "Domain Knowledge"
      }
    },
    "dimensions": {
      "Category": "Animation",
      "Signature": "Primary Fingerprint"
    },
    "confusions": [
      "Neighboring Concept"
    ],
    "difficulty": 2,
    "confidence": {
      "signature": "High"
    }
  },
  {
    "observation_id": "creative_arts_animation_timing_0007",
    "universe": "creative_arts",
    "world": "animation",
    "subcategory": "timing",
    "entity": "Timing Concept 7",
    "entity_type": "Concept",
    "features": {
      "visual": {
        "signature": "Recognition Cue"
      },
      "semantic": {
        "context": "Domain Knowledge"
      }
    },
    "dimensions": {
      "Category": "Animation",
      "Signature": "Primary Fingerprint"
    },
    "confusions": [
      "Neighboring Concept"
    ],
    "difficulty": 3,
    "confidence": {
      "signature": "High"
    }
  },
  {
    "observation_id": "creative_arts_animation_timing_0008",
    "universe": "creative_arts",
    "world": "animation",
    "subcategory": "timing",
    "entity": "Timing Concept 8",
    "entity_type": "Concept",
    "features": {
      "visual": {
        "signature": "Recognition Cue"
      },
      "semantic": {
        "context": "Domain Knowledge"
      }
    },
    "dimensions": {
      "Category": "Animation",
      "Signature": "Primary Fingerprint"
    },
    "confusions": [
      "Neighboring Concept"
    ],
    "difficulty": 4,
    "confidence": {
      "signature": "High"
    }
  },
  {
    "observation_id": "creative_arts_animation_timing_0009",
    "universe": "creative_arts",
    "world": "animation",
    "subcategory": "timing",
    "entity": "Timing Concept 9",
    "entity_type": "Concept",
    "features": {
      "visual": {
        "signature": "Recognition Cue"
      },
      "semantic": {
        "context": "Domain Knowledge"
      }
    },
    "dimensions": {
      "Category": "Animation",
      "Signature": "Primary Fingerprint"
    },
    "confusions": [
      "Neighboring Concept"
    ],
    "difficulty": 5,
    "confidence": {
      "signature": "High"
    }
  },
  {
    "observation_id": "creative_arts_animation_timing_0010",
    "universe": "creative_arts",
    "world": "animation",
    "subcategory": "timing",
    "entity": "Timing Concept 10",
    "entity_type": "Concept",
    "features": {
      "visual": {
        "signature": "Recognition Cue"
      },
      "semantic": {
        "context": "Domain Knowledge"
      }
    },
    "dimensions": {
      "Category": "Animation",
      "Signature": "Primary Fingerprint"
    },
    "confusions": [
      "Neighboring Concept"
    ],
    "difficulty": 1,
    "confidence": {
      "signature": "High"
    }
  },
  {
    "observation_id": "creative_arts_animation_timing_0011",
    "universe": "creative_arts",
    "world": "animation",
    "subcategory": "timing",
    "entity": "Timing Concept 11",
    "entity_type": "Concept",
    "features": {
      "visual": {
        "signature": "Recognition Cue"
      },
      "semantic": {
        "context": "Domain Knowledge"
      }
    },
    "dimensions": {
      "Category": "Animation",
      "Signature": "Primary Fingerprint"
    },
    "confusions": [
      "Neighboring Concept"
    ],
    "difficulty": 2,
    "confidence": {
      "signature": "High"
    }
  },
  {
    "observation_id": "creative_arts_animation_timing_0012",
    "universe": "creative_arts",
    "world": "animation",
    "subcategory": "timing",
    "entity": "Timing Concept 12",
    "entity_type": "Concept",
    "features": {
      "visual": {
        "signature": "Recognition Cue"
      },
      "semantic": {
        "context": "Domain Knowledge"
      }
    },
    "dimensions": {
      "Category": "Animation",
      "Signature": "Primary Fingerprint"
    },
    "confusions": [
      "Neighboring Concept"
    ],
    "difficulty": 3,
    "confidence": {
      "signature": "High"
    }
  },
  {
    "observation_id": "creative_arts_animation_timing_0013",
    "universe": "creative_arts",
    "world": "animation",
    "subcategory": "timing",
    "entity": "Timing Concept 13",
    "entity_type": "Concept",
    "features": {
      "visual": {
        "signature": "Recognition Cue"
      },
      "semantic": {
        "context": "Domain Knowledge"
      }
    },
    "dimensions": {
      "Category": "Animation",
      "Signature": "Primary Fingerprint"
    },
    "confusions": [
      "Neighboring Concept"
    ],
    "difficulty": 4,
    "confidence": {
      "signature": "High"
    }
  },
  {
    "observation_id": "creative_arts_animation_timing_0014",
    "universe": "creative_arts",
    "world": "animation",
    "subcategory": "timing",
    "entity": "Timing Concept 14",
    "entity_type": "Concept",
    "features": {
      "visual": {
        "signature": "Recognition Cue"
      },
      "semantic": {
        "context": "Domain Knowledge"
      }
    },
    "dimensions": {
      "Category": "Animation",
      "Signature": "Primary Fingerprint"
    },
    "confusions": [
      "Neighboring Concept"
    ],
    "difficulty": 5,
    "confidence": {
      "signature": "High"
    }
  },
  {
    "observation_id": "creative_arts_animation_timing_0015",
    "universe": "creative_arts",
    "world": "animation",
    "subcategory": "timing",
    "entity": "Timing Concept 15",
    "entity_type": "Concept",
    "features": {
      "visual": {
        "signature": "Recognition Cue"
      },
      "semantic": {
        "context": "Domain Knowledge"
      }
    },
    "dimensions": {
      "Category": "Animation",
      "Signature": "Primary Fingerprint"
    },
    "confusions": [
      "Neighboring Concept"
    ],
    "difficulty": 1,
    "confidence": {
      "signature": "High"
    }
  },
  {
    "observation_id": "creative_arts_animation_timing_0016",
    "universe": "creative_arts",
    "world": "animation",
    "subcategory": "timing",
    "entity": "Timing Concept 16",
    "entity_type": "Concept",
    "features": {
      "visual": {
        "signature": "Recognition Cue"
      },
      "semantic": {
        "context": "Domain Knowledge"
      }
    },
    "dimensions": {
      "Category": "Animation",
      "Signature": "Primary Fingerprint"
    },
    "confusions": [
      "Neighboring Concept"
    ],
    "difficulty": 2,
    "confidence": {
      "signature": "High"
    }
  },
  {
    "observation_id": "creative_arts_animation_timing_0017",
    "universe": "creative_arts",
    "world": "animation",
    "subcategory": "timing",
    "entity": "Timing Concept 17",
    "entity_type": "Concept",
    "features": {
      "visual": {
        "signature": "Recognition Cue"
      },
      "semantic": {
        "context": "Domain Knowledge"
      }
    },
    "dimensions": {
      "Category": "Animation",
      "Signature": "Primary Fingerprint"
    },
    "confusions": [
      "Neighboring Concept"
    ],
    "difficulty": 3,
    "confidence": {
      "signature": "High"
    }
  },
  {
    "observation_id": "creative_arts_animation_timing_0018",
    "universe": "creative_arts",
    "world": "animation",
    "subcategory": "timing",
    "entity": "Timing Concept 18",
    "entity_type": "Concept",
    "features": {
      "visual": {
        "signature": "Recognition Cue"
      },
      "semantic": {
        "context": "Domain Knowledge"
      }
    },
    "dimensions": {
      "Category": "Animation",
      "Signature": "Primary Fingerprint"
    },
    "confusions": [
      "Neighboring Concept"
    ],
    "difficulty": 4,
    "confidence": {
      "signature": "High"
    }
  },
  {
    "observation_id": "creative_arts_animation_timing_0019",
    "universe": "creative_arts",
    "world": "animation",
    "subcategory": "timing",
    "entity": "Timing Concept 19",
    "entity_type": "Concept",
    "features": {
      "visual": {
        "signature": "Recognition Cue"
      },
      "semantic": {
        "context": "Domain Knowledge"
      }
    },
    "dimensions": {
      "Category": "Animation",
      "Signature": "Primary Fingerprint"
    },
    "confusions": [
      "Neighboring Concept"
    ],
    "difficulty": 5,
    "confidence": {
      "signature": "High"
    }
  },
  {
    "observation_id": "creative_arts_animation_timing_0020",
    "universe": "creative_arts",
    "world": "animation",
    "subcategory": "timing",
    "entity": "Timing Concept 20",
    "entity_type": "Concept",
    "features": {
      "visual": {
        "signature": "Recognition Cue"
      },
      "semantic": {
        "context": "Domain Knowledge"
      }
    },
    "dimensions": {
      "Category": "Animation",
      "Signature": "Primary Fingerprint"
    },
    "confusions": [
      "Neighboring Concept"
    ],
    "difficulty": 1,
    "confidence": {
      "signature": "High"
    }
  },
  {
    "observation_id": "creative_arts_animation_timing_0021",
    "universe": "creative_arts",
    "world": "animation",
    "subcategory": "timing",
    "entity": "Timing Concept 21",
    "entity_type": "Concept",
    "features": {
      "visual": {
        "signature": "Recognition Cue"
      },
      "semantic": {
        "context": "Domain Knowledge"
      }
    },
    "dimensions": {
      "Category": "Animation",
      "Signature": "Primary Fingerprint"
    },
    "confusions": [
      "Neighboring Concept"
    ],
    "difficulty": 2,
    "confidence": {
      "signature": "High"
    }
  },
  {
    "observation_id": "creative_arts_animation_timing_0022",
    "universe": "creative_arts",
    "world": "animation",
    "subcategory": "timing",
    "entity": "Timing Concept 22",
    "entity_type": "Concept",
    "features": {
      "visual": {
        "signature": "Recognition Cue"
      },
      "semantic": {
        "context": "Domain Knowledge"
      }
    },
    "dimensions": {
      "Category": "Animation",
      "Signature": "Primary Fingerprint"
    },
    "confusions": [
      "Neighboring Concept"
    ],
    "difficulty": 3,
    "confidence": {
      "signature": "High"
    }
  },
  {
    "observation_id": "creative_arts_animation_timing_0023",
    "universe": "creative_arts",
    "world": "animation",
    "subcategory": "timing",
    "entity": "Timing Concept 23",
    "entity_type": "Concept",
    "features": {
      "visual": {
        "signature": "Recognition Cue"
      },
      "semantic": {
        "context": "Domain Knowledge"
      }
    },
    "dimensions": {
      "Category": "Animation",
      "Signature": "Primary Fingerprint"
    },
    "confusions": [
      "Neighboring Concept"
    ],
    "difficulty": 4,
    "confidence": {
      "signature": "High"
    }
  },
  {
    "observation_id": "creative_arts_animation_timing_0024",
    "universe": "creative_arts",
    "world": "animation",
    "subcategory": "timing",
    "entity": "Timing Concept 24",
    "entity_type": "Concept",
    "features": {
      "visual": {
        "signature": "Recognition Cue"
      },
      "semantic": {
        "context": "Domain Knowledge"
      }
    },
    "dimensions": {
      "Category": "Animation",
      "Signature": "Primary Fingerprint"
    },
    "confusions": [
      "Neighboring Concept"
    ],
    "difficulty": 5,
    "confidence": {
      "signature": "High"
    }
  },
  {
    "observation_id": "creative_arts_animation_timing_0025",
    "universe": "creative_arts",
    "world": "animation",
    "subcategory": "timing",
    "entity": "Timing Concept 25",
    "entity_type": "Concept",
    "features": {
      "visual": {
        "signature": "Recognition Cue"
      },
      "semantic": {
        "context": "Domain Knowledge"
      }
    },
    "dimensions": {
      "Category": "Animation",
      "Signature": "Primary Fingerprint"
    },
    "confusions": [
      "Neighboring Concept"
    ],
    "difficulty": 1,
    "confidence": {
      "signature": "High"
    }
  },
  {
    "observation_id": "creative_arts_animation_timing_0026",
    "universe": "creative_arts",
    "world": "animation",
    "subcategory": "timing",
    "entity": "Timing Concept 26",
    "entity_type": "Concept",
    "features": {
      "visual": {
        "signature": "Recognition Cue"
      },
      "semantic": {
        "context": "Domain Knowledge"
      }
    },
    "dimensions": {
      "Category": "Animation",
      "Signature": "Primary Fingerprint"
    },
    "confusions": [
      "Neighboring Concept"
    ],
    "difficulty": 2,
    "confidence": {
      "signature": "High"
    }
  },
  {
    "observation_id": "creative_arts_animation_timing_0027",
    "universe": "creative_arts",
    "world": "animation",
    "subcategory": "timing",
    "entity": "Timing Concept 27",
    "entity_type": "Concept",
    "features": {
      "visual": {
        "signature": "Recognition Cue"
      },
      "semantic": {
        "context": "Domain Knowledge"
      }
    },
    "dimensions": {
      "Category": "Animation",
      "Signature": "Primary Fingerprint"
    },
    "confusions": [
      "Neighboring Concept"
    ],
    "difficulty": 3,
    "confidence": {
      "signature": "High"
    }
  },
  {
    "observation_id": "creative_arts_animation_timing_0028",
    "universe": "creative_arts",
    "world": "animation",
    "subcategory": "timing",
    "entity": "Timing Concept 28",
    "entity_type": "Concept",
    "features": {
      "visual": {
        "signature": "Recognition Cue"
      },
      "semantic": {
        "context": "Domain Knowledge"
      }
    },
    "dimensions": {
      "Category": "Animation",
      "Signature": "Primary Fingerprint"
    },
    "confusions": [
      "Neighboring Concept"
    ],
    "difficulty": 4,
    "confidence": {
      "signature": "High"
    }
  },
  {
    "observation_id": "creative_arts_animation_timing_0029",
    "universe": "creative_arts",
    "world": "animation",
    "subcategory": "timing",
    "entity": "Timing Concept 29",
    "entity_type": "Concept",
    "features": {
      "visual": {
        "signature": "Recognition Cue"
      },
      "semantic": {
        "context": "Domain Knowledge"
      }
    },
    "dimensions": {
      "Category": "Animation",
      "Signature": "Primary Fingerprint"
    },
    "confusions": [
      "Neighboring Concept"
    ],
    "difficulty": 5,
    "confidence": {
      "signature": "High"
    }
  },
  {
    "observation_id": "creative_arts_animation_timing_0030",
    "universe": "creative_arts",
    "world": "animation",
    "subcategory": "timing",
    "entity": "Timing Concept 30",
    "entity_type": "Concept",
    "features": {
      "visual": {
        "signature": "Recognition Cue"
      },
      "semantic": {
        "context": "Domain Knowledge"
      }
    },
    "dimensions": {
      "Category": "Animation",
      "Signature": "Primary Fingerprint"
    },
    "confusions": [
      "Neighboring Concept"
    ],
    "difficulty": 1,
    "confidence": {
      "signature": "High"
    }
  },
  {
    "observation_id": "creative_arts_animation_timing_0031",
    "universe": "creative_arts",
    "world": "animation",
    "subcategory": "timing",
    "entity": "Timing Concept 31",
    "entity_type": "Concept",
    "features": {
      "visual": {
        "signature": "Recognition Cue"
      },
      "semantic": {
        "context": "Domain Knowledge"
      }
    },
    "dimensions": {
      "Category": "Animation",
      "Signature": "Primary Fingerprint"
    },
    "confusions": [
      "Neighboring Concept"
    ],
    "difficulty": 2,
    "confidence": {
      "signature": "High"
    }
  },
  {
    "observation_id": "creative_arts_animation_timing_0032",
    "universe": "creative_arts",
    "world": "animation",
    "subcategory": "timing",
    "entity": "Timing Concept 32",
    "entity_type": "Concept",
    "features": {
      "visual": {
        "signature": "Recognition Cue"
      },
      "semantic": {
        "context": "Domain Knowledge"
      }
    },
    "dimensions": {
      "Category": "Animation",
      "Signature": "Primary Fingerprint"
    },
    "confusions": [
      "Neighboring Concept"
    ],
    "difficulty": 3,
    "confidence": {
      "signature": "High"
    }
  },
  {
    "observation_id": "creative_arts_animation_timing_0033",
    "universe": "creative_arts",
    "world": "animation",
    "subcategory": "timing",
    "entity": "Timing Concept 33",
    "entity_type": "Concept",
    "features": {
      "visual": {
        "signature": "Recognition Cue"
      },
      "semantic": {
        "context": "Domain Knowledge"
      }
    },
    "dimensions": {
      "Category": "Animation",
      "Signature": "Primary Fingerprint"
    },
    "confusions": [
      "Neighboring Concept"
    ],
    "difficulty": 4,
    "confidence": {
      "signature": "High"
    }
  },
  {
    "observation_id": "creative_arts_animation_timing_0034",
    "universe": "creative_arts",
    "world": "animation",
    "subcategory": "timing",
    "entity": "Timing Concept 34",
    "entity_type": "Concept",
    "features": {
      "visual": {
        "signature": "Recognition Cue"
      },
      "semantic": {
        "context": "Domain Knowledge"
      }
    },
    "dimensions": {
      "Category": "Animation",
      "Signature": "Primary Fingerprint"
    },
    "confusions": [
      "Neighboring Concept"
    ],
    "difficulty": 5,
    "confidence": {
      "signature": "High"
    }
  },
  {
    "observation_id": "creative_arts_animation_timing_0035",
    "universe": "creative_arts",
    "world": "animation",
    "subcategory": "timing",
    "entity": "Timing Concept 35",
    "entity_type": "Concept",
    "features": {
      "visual": {
        "signature": "Recognition Cue"
      },
      "semantic": {
        "context": "Domain Knowledge"
      }
    },
    "dimensions": {
      "Category": "Animation",
      "Signature": "Primary Fingerprint"
    },
    "confusions": [
      "Neighboring Concept"
    ],
    "difficulty": 1,
    "confidence": {
      "signature": "High"
    }
  },
  {
    "observation_id": "creative_arts_animation_timing_0036",
    "universe": "creative_arts",
    "world": "animation",
    "subcategory": "timing",
    "entity": "Timing Concept 36",
    "entity_type": "Concept",
    "features": {
      "visual": {
        "signature": "Recognition Cue"
      },
      "semantic": {
        "context": "Domain Knowledge"
      }
    },
    "dimensions": {
      "Category": "Animation",
      "Signature": "Primary Fingerprint"
    },
    "confusions": [
      "Neighboring Concept"
    ],
    "difficulty": 2,
    "confidence": {
      "signature": "High"
    }
  },
  {
    "observation_id": "creative_arts_animation_timing_0037",
    "universe": "creative_arts",
    "world": "animation",
    "subcategory": "timing",
    "entity": "Timing Concept 37",
    "entity_type": "Concept",
    "features": {
      "visual": {
        "signature": "Recognition Cue"
      },
      "semantic": {
        "context": "Domain Knowledge"
      }
    },
    "dimensions": {
      "Category": "Animation",
      "Signature": "Primary Fingerprint"
    },
    "confusions": [
      "Neighboring Concept"
    ],
    "difficulty": 3,
    "confidence": {
      "signature": "High"
    }
  },
  {
    "observation_id": "creative_arts_animation_timing_0038",
    "universe": "creative_arts",
    "world": "animation",
    "subcategory": "timing",
    "entity": "Timing Concept 38",
    "entity_type": "Concept",
    "features": {
      "visual": {
        "signature": "Recognition Cue"
      },
      "semantic": {
        "context": "Domain Knowledge"
      }
    },
    "dimensions": {
      "Category": "Animation",
      "Signature": "Primary Fingerprint"
    },
    "confusions": [
      "Neighboring Concept"
    ],
    "difficulty": 4,
    "confidence": {
      "signature": "High"
    }
  },
  {
    "observation_id": "creative_arts_animation_timing_0039",
    "universe": "creative_arts",
    "world": "animation",
    "subcategory": "timing",
    "entity": "Timing Concept 39",
    "entity_type": "Concept",
    "features": {
      "visual": {
        "signature": "Recognition Cue"
      },
      "semantic": {
        "context": "Domain Knowledge"
      }
    },
    "dimensions": {
      "Category": "Animation",
      "Signature": "Primary Fingerprint"
    },
    "confusions": [
      "Neighboring Concept"
    ],
    "difficulty": 5,
    "confidence": {
      "signature": "High"
    }
  },
  {
    "observation_id": "creative_arts_animation_timing_0040",
    "universe": "creative_arts",
    "world": "animation",
    "subcategory": "timing",
    "entity": "Timing Concept 40",
    "entity_type": "Concept",
    "features": {
      "visual": {
        "signature": "Recognition Cue"
      },
      "semantic": {
        "context": "Domain Knowledge"
      }
    },
    "dimensions": {
      "Category": "Animation",
      "Signature": "Primary Fingerprint"
    },
    "confusions": [
      "Neighboring Concept"
    ],
    "difficulty": 1,
    "confidence": {
      "signature": "High"
    }
  },
  {
    "observation_id": "creative_arts_animation_timing_0041",
    "universe": "creative_arts",
    "world": "animation",
    "subcategory": "timing",
    "entity": "Timing Concept 41",
    "entity_type": "Concept",
    "features": {
      "visual": {
        "signature": "Recognition Cue"
      },
      "semantic": {
        "context": "Domain Knowledge"
      }
    },
    "dimensions": {
      "Category": "Animation",
      "Signature": "Primary Fingerprint"
    },
    "confusions": [
      "Neighboring Concept"
    ],
    "difficulty": 2,
    "confidence": {
      "signature": "High"
    }
  },
  {
    "observation_id": "creative_arts_animation_timing_0042",
    "universe": "creative_arts",
    "world": "animation",
    "subcategory": "timing",
    "entity": "Timing Concept 42",
    "entity_type": "Concept",
    "features": {
      "visual": {
        "signature": "Recognition Cue"
      },
      "semantic": {
        "context": "Domain Knowledge"
      }
    },
    "dimensions": {
      "Category": "Animation",
      "Signature": "Primary Fingerprint"
    },
    "confusions": [
      "Neighboring Concept"
    ],
    "difficulty": 3,
    "confidence": {
      "signature": "High"
    }
  },
  {
    "observation_id": "creative_arts_animation_timing_0043",
    "universe": "creative_arts",
    "world": "animation",
    "subcategory": "timing",
    "entity": "Timing Concept 43",
    "entity_type": "Concept",
    "features": {
      "visual": {
        "signature": "Recognition Cue"
      },
      "semantic": {
        "context": "Domain Knowledge"
      }
    },
    "dimensions": {
      "Category": "Animation",
      "Signature": "Primary Fingerprint"
    },
    "confusions": [
      "Neighboring Concept"
    ],
    "difficulty": 4,
    "confidence": {
      "signature": "High"
    }
  },
  {
    "observation_id": "creative_arts_animation_timing_0044",
    "universe": "creative_arts",
    "world": "animation",
    "subcategory": "timing",
    "entity": "Timing Concept 44",
    "entity_type": "Concept",
    "features": {
      "visual": {
        "signature": "Recognition Cue"
      },
      "semantic": {
        "context": "Domain Knowledge"
      }
    },
    "dimensions": {
      "Category": "Animation",
      "Signature": "Primary Fingerprint"
    },
    "confusions": [
      "Neighboring Concept"
    ],
    "difficulty": 5,
    "confidence": {
      "signature": "High"
    }
  },
  {
    "observation_id": "creative_arts_animation_timing_0045",
    "universe": "creative_arts",
    "world": "animation",
    "subcategory": "timing",
    "entity": "Timing Concept 45",
    "entity_type": "Concept",
    "features": {
      "visual": {
        "signature": "Recognition Cue"
      },
      "semantic": {
        "context": "Domain Knowledge"
      }
    },
    "dimensions": {
      "Category": "Animation",
      "Signature": "Primary Fingerprint"
    },
    "confusions": [
      "Neighboring Concept"
    ],
    "difficulty": 1,
    "confidence": {
      "signature": "High"
    }
  },
  {
    "observation_id": "creative_arts_animation_timing_0046",
    "universe": "creative_arts",
    "world": "animation",
    "subcategory": "timing",
    "entity": "Timing Concept 46",
    "entity_type": "Concept",
    "features": {
      "visual": {
        "signature": "Recognition Cue"
      },
      "semantic": {
        "context": "Domain Knowledge"
      }
    },
    "dimensions": {
      "Category": "Animation",
      "Signature": "Primary Fingerprint"
    },
    "confusions": [
      "Neighboring Concept"
    ],
    "difficulty": 2,
    "confidence": {
      "signature": "High"
    }
  },
  {
    "observation_id": "creative_arts_animation_timing_0047",
    "universe": "creative_arts",
    "world": "animation",
    "subcategory": "timing",
    "entity": "Timing Concept 47",
    "entity_type": "Concept",
    "features": {
      "visual": {
        "signature": "Recognition Cue"
      },
      "semantic": {
        "context": "Domain Knowledge"
      }
    },
    "dimensions": {
      "Category": "Animation",
      "Signature": "Primary Fingerprint"
    },
    "confusions": [
      "Neighboring Concept"
    ],
    "difficulty": 3,
    "confidence": {
      "signature": "High"
    }
  },
  {
    "observation_id": "creative_arts_animation_timing_0048",
    "universe": "creative_arts",
    "world": "animation",
    "subcategory": "timing",
    "entity": "Timing Concept 48",
    "entity_type": "Concept",
    "features": {
      "visual": {
        "signature": "Recognition Cue"
      },
      "semantic": {
        "context": "Domain Knowledge"
      }
    },
    "dimensions": {
      "Category": "Animation",
      "Signature": "Primary Fingerprint"
    },
    "confusions": [
      "Neighboring Concept"
    ],
    "difficulty": 4,
    "confidence": {
      "signature": "High"
    }
  },
  {
    "observation_id": "creative_arts_animation_timing_0049",
    "universe": "creative_arts",
    "world": "animation",
    "subcategory": "timing",
    "entity": "Timing Concept 49",
    "entity_type": "Concept",
    "features": {
      "visual": {
        "signature": "Recognition Cue"
      },
      "semantic": {
        "context": "Domain Knowledge"
      }
    },
    "dimensions": {
      "Category": "Animation",
      "Signature": "Primary Fingerprint"
    },
    "confusions": [
      "Neighboring Concept"
    ],
    "difficulty": 5,
    "confidence": {
      "signature": "High"
    }
  },
  {
    "observation_id": "creative_arts_animation_timing_0050",
    "universe": "creative_arts",
    "world": "animation",
    "subcategory": "timing",
    "entity": "Timing Concept 50",
    "entity_type": "Concept",
    "features": {
      "visual": {
        "signature": "Recognition Cue"
      },
      "semantic": {
        "context": "Domain Knowledge"
      }
    },
    "dimensions": {
      "Category": "Animation",
      "Signature": "Primary Fingerprint"
    },
    "confusions": [
      "Neighboring Concept"
    ],
    "difficulty": 1,
    "confidence": {
      "signature": "High"
    }
  },
  {
    "observation_id": "creative_arts_animation_timing_0051",
    "universe": "creative_arts",
    "world": "animation",
    "subcategory": "timing",
    "entity": "Timing Concept 51",
    "entity_type": "Concept",
    "features": {
      "visual": {
        "signature": "Recognition Cue"
      },
      "semantic": {
        "context": "Domain Knowledge"
      }
    },
    "dimensions": {
      "Category": "Animation",
      "Signature": "Primary Fingerprint"
    },
    "confusions": [
      "Neighboring Concept"
    ],
    "difficulty": 2,
    "confidence": {
      "signature": "High"
    }
  },
  {
    "observation_id": "creative_arts_animation_timing_0052",
    "universe": "creative_arts",
    "world": "animation",
    "subcategory": "timing",
    "entity": "Timing Concept 52",
    "entity_type": "Concept",
    "features": {
      "visual": {
        "signature": "Recognition Cue"
      },
      "semantic": {
        "context": "Domain Knowledge"
      }
    },
    "dimensions": {
      "Category": "Animation",
      "Signature": "Primary Fingerprint"
    },
    "confusions": [
      "Neighboring Concept"
    ],
    "difficulty": 3,
    "confidence": {
      "signature": "High"
    }
  },
  {
    "observation_id": "creative_arts_animation_timing_0053",
    "universe": "creative_arts",
    "world": "animation",
    "subcategory": "timing",
    "entity": "Timing Concept 53",
    "entity_type": "Concept",
    "features": {
      "visual": {
        "signature": "Recognition Cue"
      },
      "semantic": {
        "context": "Domain Knowledge"
      }
    },
    "dimensions": {
      "Category": "Animation",
      "Signature": "Primary Fingerprint"
    },
    "confusions": [
      "Neighboring Concept"
    ],
    "difficulty": 4,
    "confidence": {
      "signature": "High"
    }
  },
  {
    "observation_id": "creative_arts_animation_timing_0054",
    "universe": "creative_arts",
    "world": "animation",
    "subcategory": "timing",
    "entity": "Timing Concept 54",
    "entity_type": "Concept",
    "features": {
      "visual": {
        "signature": "Recognition Cue"
      },
      "semantic": {
        "context": "Domain Knowledge"
      }
    },
    "dimensions": {
      "Category": "Animation",
      "Signature": "Primary Fingerprint"
    },
    "confusions": [
      "Neighboring Concept"
    ],
    "difficulty": 5,
    "confidence": {
      "signature": "High"
    }
  },
  {
    "observation_id": "creative_arts_animation_timing_0055",
    "universe": "creative_arts",
    "world": "animation",
    "subcategory": "timing",
    "entity": "Timing Concept 55",
    "entity_type": "Concept",
    "features": {
      "visual": {
        "signature": "Recognition Cue"
      },
      "semantic": {
        "context": "Domain Knowledge"
      }
    },
    "dimensions": {
      "Category": "Animation",
      "Signature": "Primary Fingerprint"
    },
    "confusions": [
      "Neighboring Concept"
    ],
    "difficulty": 1,
    "confidence": {
      "signature": "High"
    }
  },
  {
    "observation_id": "creative_arts_animation_timing_0056",
    "universe": "creative_arts",
    "world": "animation",
    "subcategory": "timing",
    "entity": "Timing Concept 56",
    "entity_type": "Concept",
    "features": {
      "visual": {
        "signature": "Recognition Cue"
      },
      "semantic": {
        "context": "Domain Knowledge"
      }
    },
    "dimensions": {
      "Category": "Animation",
      "Signature": "Primary Fingerprint"
    },
    "confusions": [
      "Neighboring Concept"
    ],
    "difficulty": 2,
    "confidence": {
      "signature": "High"
    }
  },
  {
    "observation_id": "creative_arts_animation_timing_0057",
    "universe": "creative_arts",
    "world": "animation",
    "subcategory": "timing",
    "entity": "Timing Concept 57",
    "entity_type": "Concept",
    "features": {
      "visual": {
        "signature": "Recognition Cue"
      },
      "semantic": {
        "context": "Domain Knowledge"
      }
    },
    "dimensions": {
      "Category": "Animation",
      "Signature": "Primary Fingerprint"
    },
    "confusions": [
      "Neighboring Concept"
    ],
    "difficulty": 3,
    "confidence": {
      "signature": "High"
    }
  },
  {
    "observation_id": "creative_arts_animation_timing_0058",
    "universe": "creative_arts",
    "world": "animation",
    "subcategory": "timing",
    "entity": "Timing Concept 58",
    "entity_type": "Concept",
    "features": {
      "visual": {
        "signature": "Recognition Cue"
      },
      "semantic": {
        "context": "Domain Knowledge"
      }
    },
    "dimensions": {
      "Category": "Animation",
      "Signature": "Primary Fingerprint"
    },
    "confusions": [
      "Neighboring Concept"
    ],
    "difficulty": 4,
    "confidence": {
      "signature": "High"
    }
  },
  {
    "observation_id": "creative_arts_animation_timing_0059",
    "universe": "creative_arts",
    "world": "animation",
    "subcategory": "timing",
    "entity": "Timing Concept 59",
    "entity_type": "Concept",
    "features": {
      "visual": {
        "signature": "Recognition Cue"
      },
      "semantic": {
        "context": "Domain Knowledge"
      }
    },
    "dimensions": {
      "Category": "Animation",
      "Signature": "Primary Fingerprint"
    },
    "confusions": [
      "Neighboring Concept"
    ],
    "difficulty": 5,
    "confidence": {
      "signature": "High"
    }
  },
  {
    "observation_id": "creative_arts_animation_timing_0060",
    "universe": "creative_arts",
    "world": "animation",
    "subcategory": "timing",
    "entity": "Timing Concept 60",
    "entity_type": "Concept",
    "features": {
      "visual": {
        "signature": "Recognition Cue"
      },
      "semantic": {
        "context": "Domain Knowledge"
      }
    },
    "dimensions": {
      "Category": "Animation",
      "Signature": "Primary Fingerprint"
    },
    "confusions": [
      "Neighboring Concept"
    ],
    "difficulty": 1,
    "confidence": {
      "signature": "High"
    }
  },
  {
    "observation_id": "creative_arts_animation_timing_0061",
    "universe": "creative_arts",
    "world": "animation",
    "subcategory": "timing",
    "entity": "Timing Concept 61",
    "entity_type": "Concept",
    "features": {
      "visual": {
        "signature": "Recognition Cue"
      },
      "semantic": {
        "context": "Domain Knowledge"
      }
    },
    "dimensions": {
      "Category": "Animation",
      "Signature": "Primary Fingerprint"
    },
    "confusions": [
      "Neighboring Concept"
    ],
    "difficulty": 2,
    "confidence": {
      "signature": "High"
    }
  },
  {
    "observation_id": "creative_arts_animation_timing_0062",
    "universe": "creative_arts",
    "world": "animation",
    "subcategory": "timing",
    "entity": "Timing Concept 62",
    "entity_type": "Concept",
    "features": {
      "visual": {
        "signature": "Recognition Cue"
      },
      "semantic": {
        "context": "Domain Knowledge"
      }
    },
    "dimensions": {
      "Category": "Animation",
      "Signature": "Primary Fingerprint"
    },
    "confusions": [
      "Neighboring Concept"
    ],
    "difficulty": 3,
    "confidence": {
      "signature": "High"
    }
  },
  {
    "observation_id": "creative_arts_animation_timing_0063",
    "universe": "creative_arts",
    "world": "animation",
    "subcategory": "timing",
    "entity": "Timing Concept 63",
    "entity_type": "Concept",
    "features": {
      "visual": {
        "signature": "Recognition Cue"
      },
      "semantic": {
        "context": "Domain Knowledge"
      }
    },
    "dimensions": {
      "Category": "Animation",
      "Signature": "Primary Fingerprint"
    },
    "confusions": [
      "Neighboring Concept"
    ],
    "difficulty": 4,
    "confidence": {
      "signature": "High"
    }
  },
  {
    "observation_id": "creative_arts_animation_timing_0064",
    "universe": "creative_arts",
    "world": "animation",
    "subcategory": "timing",
    "entity": "Timing Concept 64",
    "entity_type": "Concept",
    "features": {
      "visual": {
        "signature": "Recognition Cue"
      },
      "semantic": {
        "context": "Domain Knowledge"
      }
    },
    "dimensions": {
      "Category": "Animation",
      "Signature": "Primary Fingerprint"
    },
    "confusions": [
      "Neighboring Concept"
    ],
    "difficulty": 5,
    "confidence": {
      "signature": "High"
    }
  },
  {
    "observation_id": "creative_arts_animation_timing_0065",
    "universe": "creative_arts",
    "world": "animation",
    "subcategory": "timing",
    "entity": "Timing Concept 65",
    "entity_type": "Concept",
    "features": {
      "visual": {
        "signature": "Recognition Cue"
      },
      "semantic": {
        "context": "Domain Knowledge"
      }
    },
    "dimensions": {
      "Category": "Animation",
      "Signature": "Primary Fingerprint"
    },
    "confusions": [
      "Neighboring Concept"
    ],
    "difficulty": 1,
    "confidence": {
      "signature": "High"
    }
  },
  {
    "observation_id": "creative_arts_animation_timing_0066",
    "universe": "creative_arts",
    "world": "animation",
    "subcategory": "timing",
    "entity": "Timing Concept 66",
    "entity_type": "Concept",
    "features": {
      "visual": {
        "signature": "Recognition Cue"
      },
      "semantic": {
        "context": "Domain Knowledge"
      }
    },
    "dimensions": {
      "Category": "Animation",
      "Signature": "Primary Fingerprint"
    },
    "confusions": [
      "Neighboring Concept"
    ],
    "difficulty": 2,
    "confidence": {
      "signature": "High"
    }
  },
  {
    "observation_id": "creative_arts_animation_timing_0067",
    "universe": "creative_arts",
    "world": "animation",
    "subcategory": "timing",
    "entity": "Timing Concept 67",
    "entity_type": "Concept",
    "features": {
      "visual": {
        "signature": "Recognition Cue"
      },
      "semantic": {
        "context": "Domain Knowledge"
      }
    },
    "dimensions": {
      "Category": "Animation",
      "Signature": "Primary Fingerprint"
    },
    "confusions": [
      "Neighboring Concept"
    ],
    "difficulty": 3,
    "confidence": {
      "signature": "High"
    }
  },
  {
    "observation_id": "creative_arts_animation_timing_0068",
    "universe": "creative_arts",
    "world": "animation",
    "subcategory": "timing",
    "entity": "Timing Concept 68",
    "entity_type": "Concept",
    "features": {
      "visual": {
        "signature": "Recognition Cue"
      },
      "semantic": {
        "context": "Domain Knowledge"
      }
    },
    "dimensions": {
      "Category": "Animation",
      "Signature": "Primary Fingerprint"
    },
    "confusions": [
      "Neighboring Concept"
    ],
    "difficulty": 4,
    "confidence": {
      "signature": "High"
    }
  },
  {
    "observation_id": "creative_arts_animation_timing_0069",
    "universe": "creative_arts",
    "world": "animation",
    "subcategory": "timing",
    "entity": "Timing Concept 69",
    "entity_type": "Concept",
    "features": {
      "visual": {
        "signature": "Recognition Cue"
      },
      "semantic": {
        "context": "Domain Knowledge"
      }
    },
    "dimensions": {
      "Category": "Animation",
      "Signature": "Primary Fingerprint"
    },
    "confusions": [
      "Neighboring Concept"
    ],
    "difficulty": 5,
    "confidence": {
      "signature": "High"
    }
  },
  {
    "observation_id": "creative_arts_animation_timing_0070",
    "universe": "creative_arts",
    "world": "animation",
    "subcategory": "timing",
    "entity": "Timing Concept 70",
    "entity_type": "Concept",
    "features": {
      "visual": {
        "signature": "Recognition Cue"
      },
      "semantic": {
        "context": "Domain Knowledge"
      }
    },
    "dimensions": {
      "Category": "Animation",
      "Signature": "Primary Fingerprint"
    },
    "confusions": [
      "Neighboring Concept"
    ],
    "difficulty": 1,
    "confidence": {
      "signature": "High"
    }
  },
  {
    "observation_id": "creative_arts_animation_timing_0071",
    "universe": "creative_arts",
    "world": "animation",
    "subcategory": "timing",
    "entity": "Timing Concept 71",
    "entity_type": "Concept",
    "features": {
      "visual": {
        "signature": "Recognition Cue"
      },
      "semantic": {
        "context": "Domain Knowledge"
      }
    },
    "dimensions": {
      "Category": "Animation",
      "Signature": "Primary Fingerprint"
    },
    "confusions": [
      "Neighboring Concept"
    ],
    "difficulty": 2,
    "confidence": {
      "signature": "High"
    }
  },
  {
    "observation_id": "creative_arts_animation_timing_0072",
    "universe": "creative_arts",
    "world": "animation",
    "subcategory": "timing",
    "entity": "Timing Concept 72",
    "entity_type": "Concept",
    "features": {
      "visual": {
        "signature": "Recognition Cue"
      },
      "semantic": {
        "context": "Domain Knowledge"
      }
    },
    "dimensions": {
      "Category": "Animation",
      "Signature": "Primary Fingerprint"
    },
    "confusions": [
      "Neighboring Concept"
    ],
    "difficulty": 3,
    "confidence": {
      "signature": "High"
    }
  },
  {
    "observation_id": "creative_arts_animation_timing_0073",
    "universe": "creative_arts",
    "world": "animation",
    "subcategory": "timing",
    "entity": "Timing Concept 73",
    "entity_type": "Concept",
    "features": {
      "visual": {
        "signature": "Recognition Cue"
      },
      "semantic": {
        "context": "Domain Knowledge"
      }
    },
    "dimensions": {
      "Category": "Animation",
      "Signature": "Primary Fingerprint"
    },
    "confusions": [
      "Neighboring Concept"
    ],
    "difficulty": 4,
    "confidence": {
      "signature": "High"
    }
  },
  {
    "observation_id": "creative_arts_animation_timing_0074",
    "universe": "creative_arts",
    "world": "animation",
    "subcategory": "timing",
    "entity": "Timing Concept 74",
    "entity_type": "Concept",
    "features": {
      "visual": {
        "signature": "Recognition Cue"
      },
      "semantic": {
        "context": "Domain Knowledge"
      }
    },
    "dimensions": {
      "Category": "Animation",
      "Signature": "Primary Fingerprint"
    },
    "confusions": [
      "Neighboring Concept"
    ],
    "difficulty": 5,
    "confidence": {
      "signature": "High"
    }
  },
  {
    "observation_id": "creative_arts_animation_timing_0075",
    "universe": "creative_arts",
    "world": "animation",
    "subcategory": "timing",
    "entity": "Timing Concept 75",
    "entity_type": "Concept",
    "features": {
      "visual": {
        "signature": "Recognition Cue"
      },
      "semantic": {
        "context": "Domain Knowledge"
      }
    },
    "dimensions": {
      "Category": "Animation",
      "Signature": "Primary Fingerprint"
    },
    "confusions": [
      "Neighboring Concept"
    ],
    "difficulty": 1,
    "confidence": {
      "signature": "High"
    }
  },
  {
    "observation_id": "creative_arts_animation_timing_0076",
    "universe": "creative_arts",
    "world": "animation",
    "subcategory": "timing",
    "entity": "Timing Concept 76",
    "entity_type": "Concept",
    "features": {
      "visual": {
        "signature": "Recognition Cue"
      },
      "semantic": {
        "context": "Domain Knowledge"
      }
    },
    "dimensions": {
      "Category": "Animation",
      "Signature": "Primary Fingerprint"
    },
    "confusions": [
      "Neighboring Concept"
    ],
    "difficulty": 2,
    "confidence": {
      "signature": "High"
    }
  },
  {
    "observation_id": "creative_arts_animation_timing_0077",
    "universe": "creative_arts",
    "world": "animation",
    "subcategory": "timing",
    "entity": "Timing Concept 77",
    "entity_type": "Concept",
    "features": {
      "visual": {
        "signature": "Recognition Cue"
      },
      "semantic": {
        "context": "Domain Knowledge"
      }
    },
    "dimensions": {
      "Category": "Animation",
      "Signature": "Primary Fingerprint"
    },
    "confusions": [
      "Neighboring Concept"
    ],
    "difficulty": 3,
    "confidence": {
      "signature": "High"
    }
  },
  {
    "observation_id": "creative_arts_animation_timing_0078",
    "universe": "creative_arts",
    "world": "animation",
    "subcategory": "timing",
    "entity": "Timing Concept 78",
    "entity_type": "Concept",
    "features": {
      "visual": {
        "signature": "Recognition Cue"
      },
      "semantic": {
        "context": "Domain Knowledge"
      }
    },
    "dimensions": {
      "Category": "Animation",
      "Signature": "Primary Fingerprint"
    },
    "confusions": [
      "Neighboring Concept"
    ],
    "difficulty": 4,
    "confidence": {
      "signature": "High"
    }
  },
  {
    "observation_id": "creative_arts_animation_timing_0079",
    "universe": "creative_arts",
    "world": "animation",
    "subcategory": "timing",
    "entity": "Timing Concept 79",
    "entity_type": "Concept",
    "features": {
      "visual": {
        "signature": "Recognition Cue"
      },
      "semantic": {
        "context": "Domain Knowledge"
      }
    },
    "dimensions": {
      "Category": "Animation",
      "Signature": "Primary Fingerprint"
    },
    "confusions": [
      "Neighboring Concept"
    ],
    "difficulty": 5,
    "confidence": {
      "signature": "High"
    }
  },
  {
    "observation_id": "creative_arts_animation_timing_0080",
    "universe": "creative_arts",
    "world": "animation",
    "subcategory": "timing",
    "entity": "Timing Concept 80",
    "entity_type": "Concept",
    "features": {
      "visual": {
        "signature": "Recognition Cue"
      },
      "semantic": {
        "context": "Domain Knowledge"
      }
    },
    "dimensions": {
      "Category": "Animation",
      "Signature": "Primary Fingerprint"
    },
    "confusions": [
      "Neighboring Concept"
    ],
    "difficulty": 1,
    "confidence": {
      "signature": "High"
    }
  },
  {
    "observation_id": "creative_arts_animation_timing_0081",
    "universe": "creative_arts",
    "world": "animation",
    "subcategory": "timing",
    "entity": "Timing Concept 81",
    "entity_type": "Concept",
    "features": {
      "visual": {
        "signature": "Recognition Cue"
      },
      "semantic": {
        "context": "Domain Knowledge"
      }
    },
    "dimensions": {
      "Category": "Animation",
      "Signature": "Primary Fingerprint"
    },
    "confusions": [
      "Neighboring Concept"
    ],
    "difficulty": 2,
    "confidence": {
      "signature": "High"
    }
  },
  {
    "observation_id": "creative_arts_animation_timing_0082",
    "universe": "creative_arts",
    "world": "animation",
    "subcategory": "timing",
    "entity": "Timing Concept 82",
    "entity_type": "Concept",
    "features": {
      "visual": {
        "signature": "Recognition Cue"
      },
      "semantic": {
        "context": "Domain Knowledge"
      }
    },
    "dimensions": {
      "Category": "Animation",
      "Signature": "Primary Fingerprint"
    },
    "confusions": [
      "Neighboring Concept"
    ],
    "difficulty": 3,
    "confidence": {
      "signature": "High"
    }
  },
  {
    "observation_id": "creative_arts_animation_timing_0083",
    "universe": "creative_arts",
    "world": "animation",
    "subcategory": "timing",
    "entity": "Timing Concept 83",
    "entity_type": "Concept",
    "features": {
      "visual": {
        "signature": "Recognition Cue"
      },
      "semantic": {
        "context": "Domain Knowledge"
      }
    },
    "dimensions": {
      "Category": "Animation",
      "Signature": "Primary Fingerprint"
    },
    "confusions": [
      "Neighboring Concept"
    ],
    "difficulty": 4,
    "confidence": {
      "signature": "High"
    }
  },
  {
    "observation_id": "creative_arts_animation_timing_0084",
    "universe": "creative_arts",
    "world": "animation",
    "subcategory": "timing",
    "entity": "Timing Concept 84",
    "entity_type": "Concept",
    "features": {
      "visual": {
        "signature": "Recognition Cue"
      },
      "semantic": {
        "context": "Domain Knowledge"
      }
    },
    "dimensions": {
      "Category": "Animation",
      "Signature": "Primary Fingerprint"
    },
    "confusions": [
      "Neighboring Concept"
    ],
    "difficulty": 5,
    "confidence": {
      "signature": "High"
    }
  },
  {
    "observation_id": "creative_arts_animation_timing_0085",
    "universe": "creative_arts",
    "world": "animation",
    "subcategory": "timing",
    "entity": "Timing Concept 85",
    "entity_type": "Concept",
    "features": {
      "visual": {
        "signature": "Recognition Cue"
      },
      "semantic": {
        "context": "Domain Knowledge"
      }
    },
    "dimensions": {
      "Category": "Animation",
      "Signature": "Primary Fingerprint"
    },
    "confusions": [
      "Neighboring Concept"
    ],
    "difficulty": 1,
    "confidence": {
      "signature": "High"
    }
  },
  {
    "observation_id": "creative_arts_animation_timing_0086",
    "universe": "creative_arts",
    "world": "animation",
    "subcategory": "timing",
    "entity": "Timing Concept 86",
    "entity_type": "Concept",
    "features": {
      "visual": {
        "signature": "Recognition Cue"
      },
      "semantic": {
        "context": "Domain Knowledge"
      }
    },
    "dimensions": {
      "Category": "Animation",
      "Signature": "Primary Fingerprint"
    },
    "confusions": [
      "Neighboring Concept"
    ],
    "difficulty": 2,
    "confidence": {
      "signature": "High"
    }
  },
  {
    "observation_id": "creative_arts_animation_timing_0087",
    "universe": "creative_arts",
    "world": "animation",
    "subcategory": "timing",
    "entity": "Timing Concept 87",
    "entity_type": "Concept",
    "features": {
      "visual": {
        "signature": "Recognition Cue"
      },
      "semantic": {
        "context": "Domain Knowledge"
      }
    },
    "dimensions": {
      "Category": "Animation",
      "Signature": "Primary Fingerprint"
    },
    "confusions": [
      "Neighboring Concept"
    ],
    "difficulty": 3,
    "confidence": {
      "signature": "High"
    }
  },
  {
    "observation_id": "creative_arts_animation_timing_0088",
    "universe": "creative_arts",
    "world": "animation",
    "subcategory": "timing",
    "entity": "Timing Concept 88",
    "entity_type": "Concept",
    "features": {
      "visual": {
        "signature": "Recognition Cue"
      },
      "semantic": {
        "context": "Domain Knowledge"
      }
    },
    "dimensions": {
      "Category": "Animation",
      "Signature": "Primary Fingerprint"
    },
    "confusions": [
      "Neighboring Concept"
    ],
    "difficulty": 4,
    "confidence": {
      "signature": "High"
    }
  },
  {
    "observation_id": "creative_arts_animation_timing_0089",
    "universe": "creative_arts",
    "world": "animation",
    "subcategory": "timing",
    "entity": "Timing Concept 89",
    "entity_type": "Concept",
    "features": {
      "visual": {
        "signature": "Recognition Cue"
      },
      "semantic": {
        "context": "Domain Knowledge"
      }
    },
    "dimensions": {
      "Category": "Animation",
      "Signature": "Primary Fingerprint"
    },
    "confusions": [
      "Neighboring Concept"
    ],
    "difficulty": 5,
    "confidence": {
      "signature": "High"
    }
  },
  {
    "observation_id": "creative_arts_animation_timing_0090",
    "universe": "creative_arts",
    "world": "animation",
    "subcategory": "timing",
    "entity": "Timing Concept 90",
    "entity_type": "Concept",
    "features": {
      "visual": {
        "signature": "Recognition Cue"
      },
      "semantic": {
        "context": "Domain Knowledge"
      }
    },
    "dimensions": {
      "Category": "Animation",
      "Signature": "Primary Fingerprint"
    },
    "confusions": [
      "Neighboring Concept"
    ],
    "difficulty": 1,
    "confidence": {
      "signature": "High"
    }
  },
  {
    "observation_id": "creative_arts_animation_timing_0091",
    "universe": "creative_arts",
    "world": "animation",
    "subcategory": "timing",
    "entity": "Timing Concept 91",
    "entity_type": "Concept",
    "features": {
      "visual": {
        "signature": "Recognition Cue"
      },
      "semantic": {
        "context": "Domain Knowledge"
      }
    },
    "dimensions": {
      "Category": "Animation",
      "Signature": "Primary Fingerprint"
    },
    "confusions": [
      "Neighboring Concept"
    ],
    "difficulty": 2,
    "confidence": {
      "signature": "High"
    }
  },
  {
    "observation_id": "creative_arts_animation_timing_0092",
    "universe": "creative_arts",
    "world": "animation",
    "subcategory": "timing",
    "entity": "Timing Concept 92",
    "entity_type": "Concept",
    "features": {
      "visual": {
        "signature": "Recognition Cue"
      },
      "semantic": {
        "context": "Domain Knowledge"
      }
    },
    "dimensions": {
      "Category": "Animation",
      "Signature": "Primary Fingerprint"
    },
    "confusions": [
      "Neighboring Concept"
    ],
    "difficulty": 3,
    "confidence": {
      "signature": "High"
    }
  },
  {
    "observation_id": "creative_arts_animation_timing_0093",
    "universe": "creative_arts",
    "world": "animation",
    "subcategory": "timing",
    "entity": "Timing Concept 93",
    "entity_type": "Concept",
    "features": {
      "visual": {
        "signature": "Recognition Cue"
      },
      "semantic": {
        "context": "Domain Knowledge"
      }
    },
    "dimensions": {
      "Category": "Animation",
      "Signature": "Primary Fingerprint"
    },
    "confusions": [
      "Neighboring Concept"
    ],
    "difficulty": 4,
    "confidence": {
      "signature": "High"
    }
  },
  {
    "observation_id": "creative_arts_animation_timing_0094",
    "universe": "creative_arts",
    "world": "animation",
    "subcategory": "timing",
    "entity": "Timing Concept 94",
    "entity_type": "Concept",
    "features": {
      "visual": {
        "signature": "Recognition Cue"
      },
      "semantic": {
        "context": "Domain Knowledge"
      }
    },
    "dimensions": {
      "Category": "Animation",
      "Signature": "Primary Fingerprint"
    },
    "confusions": [
      "Neighboring Concept"
    ],
    "difficulty": 5,
    "confidence": {
      "signature": "High"
    }
  },
  {
    "observation_id": "creative_arts_animation_timing_0095",
    "universe": "creative_arts",
    "world": "animation",
    "subcategory": "timing",
    "entity": "Timing Concept 95",
    "entity_type": "Concept",
    "features": {
      "visual": {
        "signature": "Recognition Cue"
      },
      "semantic": {
        "context": "Domain Knowledge"
      }
    },
    "dimensions": {
      "Category": "Animation",
      "Signature": "Primary Fingerprint"
    },
    "confusions": [
      "Neighboring Concept"
    ],
    "difficulty": 1,
    "confidence": {
      "signature": "High"
    }
  },
  {
    "observation_id": "creative_arts_animation_timing_0096",
    "universe": "creative_arts",
    "world": "animation",
    "subcategory": "timing",
    "entity": "Timing Concept 96",
    "entity_type": "Concept",
    "features": {
      "visual": {
        "signature": "Recognition Cue"
      },
      "semantic": {
        "context": "Domain Knowledge"
      }
    },
    "dimensions": {
      "Category": "Animation",
      "Signature": "Primary Fingerprint"
    },
    "confusions": [
      "Neighboring Concept"
    ],
    "difficulty": 2,
    "confidence": {
      "signature": "High"
    }
  },
  {
    "observation_id": "creative_arts_animation_timing_0097",
    "universe": "creative_arts",
    "world": "animation",
    "subcategory": "timing",
    "entity": "Timing Concept 97",
    "entity_type": "Concept",
    "features": {
      "visual": {
        "signature": "Recognition Cue"
      },
      "semantic": {
        "context": "Domain Knowledge"
      }
    },
    "dimensions": {
      "Category": "Animation",
      "Signature": "Primary Fingerprint"
    },
    "confusions": [
      "Neighboring Concept"
    ],
    "difficulty": 3,
    "confidence": {
      "signature": "High"
    }
  },
  {
    "observation_id": "creative_arts_animation_timing_0098",
    "universe": "creative_arts",
    "world": "animation",
    "subcategory": "timing",
    "entity": "Timing Concept 98",
    "entity_type": "Concept",
    "features": {
      "visual": {
        "signature": "Recognition Cue"
      },
      "semantic": {
        "context": "Domain Knowledge"
      }
    },
    "dimensions": {
      "Category": "Animation",
      "Signature": "Primary Fingerprint"
    },
    "confusions": [
      "Neighboring Concept"
    ],
    "difficulty": 4,
    "confidence": {
      "signature": "High"
    }
  },
  {
    "observation_id": "creative_arts_animation_timing_0099",
    "universe": "creative_arts",
    "world": "animation",
    "subcategory": "timing",
    "entity": "Timing Concept 99",
    "entity_type": "Concept",
    "features": {
      "visual": {
        "signature": "Recognition Cue"
      },
      "semantic": {
        "context": "Domain Knowledge"
      }
    },
    "dimensions": {
      "Category": "Animation",
      "Signature": "Primary Fingerprint"
    },
    "confusions": [
      "Neighboring Concept"
    ],
    "difficulty": 5,
    "confidence": {
      "signature": "High"
    }
  },
  {
    "observation_id": "creative_arts_animation_timing_0100",
    "universe": "creative_arts",
    "world": "animation",
    "subcategory": "timing",
    "entity": "Timing Concept 100",
    "entity_type": "Concept",
    "features": {
      "visual": {
        "signature": "Recognition Cue"
      },
      "semantic": {
        "context": "Domain Knowledge"
      }
    },
    "dimensions": {
      "Category": "Animation",
      "Signature": "Primary Fingerprint"
    },
    "confusions": [
      "Neighboring Concept"
    ],
    "difficulty": 1,
    "confidence": {
      "signature": "High"
    }
  }
]